Workbook

Sheet Receitas
B5: PRESTAÇÃO DE CONTAS - MAIO/2026
B7: RECIBO | C7: ALUGUEL | D7: ENCARGOS | E7: ACORDO | F7: CONDOMÍNIO | G7: IPTU | H7: SEGURO | I7: IR | J7: TX BCO | K7: HONORÁRIOS | L7: OUTROS | M7: TOTAL
B8: Rua Florêncio de Abreu, 60 | C8: 12691.68 | D8: 0 | E8: 0 | F8: 0 | G8: 11802.24 | H8: 0 | I8: 0 | J8: 0 | K8: =(C8+D8+E8)*6% -> 761.5008 | L8: 0 | M8: =C8+D8+E8+F8+G8+H8+J8+L8-I8 -> 24493.92
B9: Rua Florêncio de Abreu, 66/70/74 | C9: 27461.37 | D9: 0 | E9: 0 | F9: 0 | G9: 11802.24 | H9: 0 | I9: 0 | J9: 0 | K9: =(C9+D9+E9)*6% -> 1647.6822 | L9: 0 | M9: =C9+D9+E9+F9+G9+H9+J9+L9-I9 -> 39263.61
B10: Rua 25 de Março, 669 | C10: =114027.58-9904.5-5281.24-29071.04 -> 69770.8 | D10: 0 | E10: 0 | F10: 0 | G10: 0 | H10: 0 | I10: 0 | J10: 0 | K10: =(C10+D10+E10)*6% -> 4186.248 | L10: 0 | M10: =C10+D10+E10+F10+G10+H10+J10+L10-I10 -> 69770.8
B11: Rua 25 de Março, 661 | C11: =262539.39-97971.06-19679.85 -> 144888.48 | D11: 0 | E11: 0 | F11: 0 | G11: 29268.39 | H11: 0 | I11: =145.51+145.51+695.47+695.47+7817.55+695.49 -> 10195 | J11: 0 | K11: =(C11+D11+E11)*6% -> 8693.3088 | L11: =1051.25+4794.07+1519.59 -> 7364.91 | M11: =C11+D11+E11+F11+G11+H11+J11+L11-I11 -> 171326.78
B12: Loja 1 | C12: =14443.96-9994.94 -> 4449.02 | D12: 0 | E12: 0 | F12: 3383.25 | G12: 165.26 | H12: 0 | I12: 0 | J12: 0 | K12: =(C12+D12+E12)*6% -> 266.9412 | L12: 0 | M12: =C12+D12+E12+F12+G12+H12+J12+L12-I12 -> 7997.53
B13: Loja 1A | C13: 1436.57 | D13: 0 | E13: 0 | F13: 419.69 | G13: 29.97 | H13: 0 | I13: 0 | J13: 0 | K13: =(C13+D13+E13)*6% -> 86.1942 | L13: 0 | M13: =C13+D13+E13+F13+G13+H13+J13+L13-I13 -> 1886.23
B14: Loja 1B | C14: 1036.03 | D14: 0 | E14: 0 | F14: 269.85 | G14: 19.31 | H14: 0 | I14: 0 | J14: 0 | K14: =(C14+D14+E14)*6% -> 62.1618 | L14: 0 | M14: =C14+D14+E14+F14+G14+H14+J14+L14-I14 -> 1325.19
B15: Loja 1C | C15: 0 | D15: 0 | E15: 0 | F15: 0 | G15: 0 | H15: 0 | I15: 0 | J15: 0 | K15: =(C15+D15+E15)*6% -> 0 | L15: 0 | M15: =C15+D15+E15+F15+G15+H15+J15+L15-I15 -> 0
B16: Loja 1C - SS | C16: 0 | D16: 0 | E16: 0 | F16: 0 | G16: 0 | H16: 0 | I16: 0 | J16: 0 | K16: =(C16+D16+E16)*6% -> 0 | L16: 0 | M16: =C16+D16+E16+F16+G16+H16+J16+L16-I16 -> 0
B17: Loja 2A -FRENTE | C17: 1666.77 | D17: 0 | E17: 0 | F17: 1526.98 | G17: 104.47 | H17: 0 | I17: 0 | J17: 0 | K17: =(C17+D17+E17)*6% -> 100.0062 | L17: 209.11 | M17: =C17+D17+E17+F17+G17+H17+J17+L17-I17 -> 3507.33
B18: Loja 2-QUADRADA | C18: 1342.42 | D18: 0 | E18: 0 | F18: 1574.98 | G18: 104.47 | H18: 0 | I18: 0 | J18: 0 | K18: =(C18+D18+E18)*6% -> 80.5452 | L18: 0 | M18: =C18+D18+E18+F18+G18+H18+J18+L18-I18 -> 3021.87
B19: Loja 2-QUADRADA | C19: 1342.42 | D19: 0 | E19: 0 | F19: 1574.98 | G19: 104.47 | H19: 0 | I19: 0 | J19: 0 | K19: =(C19+D19+E19)*6% -> 80.5452 | L19: 0 | M19: =C19+D19+E19+F19+G19+H19+J19+L19-I19 -> 3021.87
B20: Loja 3 | C20: =999.66 -> 999.66 | D20: 0 | E20: 0 | F20: 2062.85 | G20: 134.79 | H20: 0 | I20: 0 | J20: 0 | K20: =(C20+D20+E20)*6% -> 59.9796 | L20: 0 | M20: =C20+D20+E20+F20+G20+H20+J20+L20-I20 -> 3197.3
B21: Loja 4 | C21: =3428.34-2376.65 -> 1051.69 | F21: 2184.84 | G21: 130.1 | K21: =(C21+D21+E21)*6% -> 63.1014 | M21: =C21+D21+E21+F21+G21+H21+J21+L21-I21 -> 3366.63
B22: Loja 5 | C22: 0 | D22: 0 | E22: 0 | F22: 0 | G22: 0 | H22: 0 | I22: 0 | J22: 0 | K22: =(C22+D22+E22)*6% -> 0 | L22: 0 | M22: =C22+D22+E22+F22+G22+H22+J22+L22-I22 -> 0
B23: Loja 5A | C23: 1754.25 | D23: 0 | E23: 0 | F23: 424.49 | G23: 0 | H23: 0 | I23: 0 | J23: 0 | K23: =(C23+D23+E23)*6% -> 105.255 | L23: 0 | M23: =C23+D23+E23+F23+G23+H23+J23+L23-I23 -> 2178.74
B24: Loja 6/7 | C24: =6275.12-2523.47-467.82-760.25 -> 2523.58 | D24: 0 | E24: 0 | F24: 3018.63 | G24: =81.57+78.84 -> 160.41 | H24: 0 | I24: 0 | J24: 0 | K24: =(C24+D24+E24)*6% -> 151.4148 | L24: 0 | M24: =C24+D24+E24+F24+G24+H24+J24+L24-I24 -> 5702.62
B25: Loja 7A | C25: 0 | D25: 0 | E25: 0 | F25: 0 | G25: 0 | H25: 0 | I25: 0 | J25: 0 | K25: =(C25+D25+E25)*6% -> 0 | L25: 0 | M25: =C25+D25+E25+F25+G25+H25+J25+L25-I25 -> 0
B26: Loja 8A | C26: 800.24 | D26: 0 | E26: 0 | F26: 666.47 | G26: 21.07 | H26: 0 | I26: 0 | J26: 0 | K26: =(C26+D26+E26)*6% -> 48.0144 | L26: 0 | M26: =C26+D26+E26+F26+G26+H26+J26+L26-I26 -> 1487.78
B27: Loja 8A | C27: 0 | D27: 0 | E27: 900 | F27: 0 | G27: 0 | H27: 0 | I27: 0 | J27: 0 | K27: =(C27+D27+E27)*6% -> 54 | L27: 0 | M27: =C27+D27+E27+F27+G27+H27+J27+L27-I27 -> 900
B28: Loja 8B | C28: =1232.86-378.73 -> 854.13 | D28: 0 | E28: 0 | F28: 435.04 | G28: 13.76 | H28: 0 | I28: 0 | J28: 0 | K28: =(C28+D28+E28)*6% -> 51.2478 | L28: 0 | M28: =C28+D28+E28+F28+G28+H28+J28+L28-I28 -> 1302.93
B29: Loja 8-8C | C29: =562.54-89.91 -> 472.63 | E29: 0 | F29: 701.03 | G29: 59.78 | K29: =(C29+D29+E29)*6% -> 28.3578 | L29: 0 | M29: =C29+D29+E29+F29+G29+H29+J29+L29-I29 -> 1233.44
B30: Loja 8D | C30: 594.74 | D30: 0 | E30: 0 | F30: 1189.92 | G30: 12.77 | H30: 0 | I30: 0 | J30: 0 | K30: =(C30+D30+E30)*6% -> 35.6844 | L30: 0 | M30: =C30+D30+E30+F30+G30+H30+J30+L30-I30 -> 1797.43
B31: Loja 9 | C31: =2285.89 -> 2285.89 | D31: 0 | E31: 0 | F31: 2511.34 | G31: 147.84 | H31: 0 | I31: 0 | J31: 0 | K31: =(C31+D31+E31)*6% -> 137.1534 | L31: 0 | M31: =C31+D31+E31+F31+G31+H31+J31+L31-I31 -> 4945.07
B32: Loja 10 | C32: =2260.34 -> 2260.34 | D32: 0 | E32: 0 | F32: 1657.58 | G32: 87.48 | H32: 0 | I32: 0 | J32: 0 | K32: =(C32+D32+E32)*6% -> 135.6204 | L32: 0 | M32: =C32+D32+E32+F32+G32+H32+J32+L32-I32 -> 4005.4
B33: Loja 11 | C33: =2322.36 -> 2322.36 | D33: 0 | E33: 0 | F33: 1575.95 | G33: 83.54 | H33: 0 | I33: 0 | J33: 0 | K33: =(C33+D33+E33)*6% -> 139.3416 | L33: 0 | M33: =C33+D33+E33+F33+G33+H33+J33+L33-I33 -> 3981.85
B34: Loja 12 | C34: 2201.65 | D34: 0 | E34: 0 | F34: 2915.68 | G34: 147.84 | H34: 0 | I34: 0 | J34: 0 | K34: =(C34+D34+E34)*6% -> 132.099 | L34: 0 | M34: =C34+D34+E34+F34+G34+H34+J34+L34-I34 -> 5265.17
B35: Loja 13 | C35: 1147.54 | D35: 0 | E35: 0 | F35: 1067.93 | G35: 63.27 | H35: 0 | I35: 0 | J35: 0 | K35: =(C35+D35+E35)*6% -> 68.8524 | L35: 0 | M35: =C35+D35+E35+F35+G35+H35+J35+L35-I35 -> 2278.74
B36: Loja 13A | C36: =1825.86-156.69 -> 1669.17 | D36: 0 | E36: 0 | F36: 1162.03 | G36: 68.8 | H36: 0 | I36: 0 | J36: 0 | K36: =(C36+D36+E36)*6% -> 100.1502 | L36: 0 | M36: =C36+D36+E36+F36+G36+H36+J36+L36-I36 -> 2900
B37: Loja 14 | C37: 876.97 | D37: 0 | E37: 0 | F37: 565.64 | G37: 97.34 | H37: 0 | I37: 0 | J37: 0 | K37: =(C37+D37+E37)*6% -> 52.6182 | L37: 0 | M37: =C37+D37+E37+F37+G37+H37+J37+L37-I37 -> 1539.95
B38: Loja 15 | C38: =1848.21 -> 1848.21 | D38: 0 | E38: 0 | F38: 681.87 | G38: 52.56 | H38: 0 | I38: 0 | J38: 0 | K38: =(C38+D38+E38)*6% -> 110.8926 | L38: 0 | M38: =C38+D38+E38+F38+G38+H38+J38+L38-I38 -> 2582.64
B39: Loja 17 | C39: 1137.96 | D39: =127.3+54.39+109.17 -> 290.86 | E39: 0 | F39: 675.04 | G39: 0 | H39: 0 | I39: 0 | J39: 0 | K39: =(C39+D39+E39)*6% -> 85.7292 | L39: 0 | M39: =C39+D39+E39+F39+G39+H39+J39+L39-I39 -> 2103.86
B40: Loja 17A | C40: =1269.15-800 -> 469.15 | D40: 0 | E40: 0 | F40: 508.95 | G40: 21.9 | H40: 0 | I40: 0 | J40: 0 | K40: =(C40+D40+E40)*6% -> 28.149 | L40: 0 | M40: =C40+D40+E40+F40+G40+H40+J40+L40-I40 -> 1000
B41: Vitrine 1A | C41: 159.56 | D41: 0 | E41: 0 | F41: 0 | G41: 0 | H41: 0 | I41: 0 | J41: 0 | K41: =(C41+D41+E41)*6% -> 9.5736 | L41: 0 | M41: =C41+D41+E41+F41+G41+H41+J41+L41-I41 -> 159.56
B42: Vitrine 03 | C42: 324.7 | D42: 0 | E42: 0 | F42: 0 | G42: 0 | H42: 0 | I42: 0 | J42: 0 | K42: =(C42+D42+E42)*6% -> 19.482 | L42: 0 | M42: =C42+D42+E42+F42+G42+H42+J42+L42-I42 -> 324.7
B43: Vitrine 4A | C43: 416.56 | D43: 0 | E43: 0 | F43: 0 | G43: 0 | H43: 0 | I43: 0 | J43: 0 | K43: =(C43+D43+E43)*6% -> 24.9936 | L43: 0 | M43: =C43+D43+E43+F43+G43+H43+J43+L43-I43 -> 416.56
B44: Vitrine 5A/5B | C44: 336.87 | D44: 0 | E44: 0 | F44: 0 | G44: 0 | H44: 0 | I44: 0 | J44: 0 | K44: =(C44+D44+E44)*6% -> 20.2122 | L44: 0 | M44: =C44+D44+E44+F44+G44+H44+J44+L44-I44 -> 336.87
B45: Vitrine 08 | C45: 164.26 | D45: 0 | E45: 0 | F45: 0 | G45: 0 | H45: 0 | I45: 0 | J45: 0 | K45: =(C45+D45+E45)*6% -> 9.8556 | L45: 0 | M45: =C45+D45+E45+F45+G45+H45+J45+L45-I45 -> 164.26
B46: Vitrine 10 | C46: 230.18 | D46: 0 | E46: 0 | F46: 0 | G46: 0 | H46: 0 | I46: 0 | J46: 0 | K46: =(C46+D46+E46)*6% -> 13.8108 | L46: 0 | M46: =C46+D46+E46+F46+G46+H46+J46+L46-I46 -> 230.18
B47: Vitrine 7A/7B | C47: 336.87 | D47: 0 | E47: 0 | F47: 0 | G47: 0 | H47: 0 | I47: 0 | J47: 0 | K47: =(C47+D47+E47)*6% -> 20.2122 | L47: 0 | M47: =C47+D47+E47+F47+G47+H47+J47+L47-I47 -> 336.87
B48: Vitrine 9A/9B | C48: 531.87 | D48: 0 | E48: 0 | F48: 0 | G48: 0 | H48: 0 | I48: 0 | J48: 0 | K48: =(C48+D48+E48)*6% -> 31.9122 | L48: 0 | M48: =C48+D48+E48+F48+G48+H48+J48+L48-I48 -> 531.87
B49: Vitrine 11A/11B | C49: 0 | D49: 0 | E49: 0 | F49: 0 | G49: 0 | H49: 0 | I49: 0 | J49: 0 | K49: 0 | L49: 0 | M49: =C49+D49+E49+F49+G49+H49+J49+L49-I49 -> 0
B50: Vitrine 12 | C50: 473.11 | D50: 0 | E50: 0 | F50: 0 | G50: 0 | H50: 0 | I50: 0 | J50: 0 | K50: =(C50+D50+E50)*6% -> 28.3866 | L50: 0 | M50: =C50+D50+E50+F50+G50+H50+J50+L50-I50 -> 473.11
B51: Vitrine 13A/13B | C51: 667.66 | D51: 0 | E51: 0 | F51: 0 | G51: 0 | H51: 0 | I51: 0 | J51: 0 | K51: =(C51+D51+E51)*6% -> 40.0596 | L51: 0 | M51: =C51+D51+E51+F51+G51+H51+J51+L51-I51 -> 667.66
B52: Vitrine 15/17 | C52: 409.05 | D52: 0 | E52: 0 | F52: 0 | G52: 0 | H52: 0 | I52: 0 | J52: 0 | K52: =(C52+D52+E52)*6% -> 24.543 | L52: 0 | M52: =C52+D52+E52+F52+G52+H52+J52+L52-I52 -> 409.05
B53: Vitrine 18 | C53: 200 | K53: =(C53+D53+E53)*6% -> 12 | M53: =C53+D53+E53+F53+G53+H53+J53+L53-I53 -> 200
B54: Vitrine 19/21/23/25 | C54: 737.53 | D54: 0 | E54: 0 | F54: 0 | G54: 0 | H54: 0 | I54: 0 | J54: 0 | K54: =(C54+D54+E54)*6% -> 44.2518 | L54: 0 | M54: =C54+D54+E54+F54+G54+H54+J54+L54-I54 -> 737.53
B55: Vitrine 20 | C55: 0 | D55: 0 | K55: =(C55+D55+E55)*6% -> 0 | M55: =C55+D55+E55+F55+G55+H55+J55+L55-I55 -> 0
B56: Vitrine 22/24 | C56: 505.31 | D56: 0 | E56: 0 | F56: 0 | G56: 0 | H56: 0 | I56: 0 | J56: 0 | K56: =(C56+D56+E56)*6% -> 30.3186 | L56: 0 | M56: =C56+D56+E56+F56+G56+H56+J56+L56-I56 -> 505.31
B57: Vitrine 26/28 | C57: =525.68 -> 525.68 | D57: 0 | E57: 0 | F57: 0 | G57: 0 | H57: 0 | I57: 0 | J57: 0 | K57: =(C57+D57+E57)*6% -> 31.5408 | L57: 0 | M57: =C57+D57+E57+F57+G57+H57+J57+L57-I57 -> 525.68
B58: Vitrine 27 | C58: 100 | D58: 0 | E58: 0 | F58: 0 | G58: 0 | H58: 0 | I58: 0 | J58: 0 | K58: =(C58+D58+E58)*6% -> 6 | L58: 0 | M58: =C58+D58+E58+F58+G58+H58+J58+L58-I58 -> 100
B59: Vitrine 29 | C59: 490.24 | D59: 0 | E59: 0 | F59: 0 | G59: 0 | H59: 0 | I59: 0 | J59: 0 | K59: =(C59+D59+E59)*6% -> 29.4144 | L59: 0 | M59: =C59+D59+E59+F59+G59+H59+J59+L59-I59 -> 490.24
B60: Vitrine 30 | C60: 341.48 | D60: 0 | E60: 0 | F60: 0 | G60: 0 | H60: 0 | I60: 0 | J60: 0 | K60: =(C60+D60+E60)*6% -> 20.4888 | L60: 0 | M60: =C60+D60+E60+F60+G60+H60+J60+L60-I60 -> 341.48
B61: Vitrine 31 | C61: 343.76 | D61: 0 | E61: 0 | F61: 0 | G61: 0 | H61: 0 | I61: 0 | J61: 0 | K61: =(C61+D61+E61)*6% -> 20.6256 | L61: 0 | M61: =C61+D61+E61+F61+G61+H61+J61+L61-I61 -> 343.76
B62: Vitrine 31 | C62: 343.76 | D62: =34.38+3.44 -> 37.82 | E62: 0 | F62: 0 | G62: 0 | H62: 0 | I62: 0 | J62: 0 | K62: =(C62+D62+E62)*6% -> 22.8948 | L62: 0 | M62: =C62+D62+E62+F62+G62+H62+J62+L62-I62 -> 381.58
B63: Vitrine 32 | C63: =488.99-209.69 -> 279.3 | D63: 0 | E63: 0 | F63: 0 | G63: 0 | H63: 0 | I63: 0 | J63: 0 | K63: =(C63+D63+E63)*6% -> 16.758 | L63: 0 | M63: =C63+D63+E63+F63+G63+H63+J63+L63-I63 -> 279.3
B64: Vitrine 33 | C64: 500 | D64: 0 | E64: 0 | F64: 0 | G64: 0 | H64: 0 | I64: 0 | J64: 0 | K64: =(C64+D64+E64)*6% -> 30 | L64: 0 | M64: =C64+D64+E64+F64+G64+H64+J64+L64-I64 -> 500
B65: Vitrine 34 | C65: 592.77 | D65: 0 | E65: 0 | F65: 0 | G65: 0 | H65: 0 | I65: 0 | J65: 0 | K65: =(C65+D65+E65)*6% -> 35.5662 | L65: 0 | M65: =C65+D65+E65+F65+G65+H65+J65+L65-I65 -> 592.77
B66: Vitrine 35 | C66: 550 | D66: 0 | E66: 0 | F66: 0 | G66: 0 | H66: 0 | I66: 0 | J66: 0 | K66: =(C66+D66+E66)*6% -> 33 | L66: 0 | M66: =C66+D66+E66+F66+G66+H66+J66+L66-I66 -> 550
B67: Vitrine 36 | C67: 550 | D67: 0 | E67: 0 | F67: 0 | G67: 0 | H67: 0 | I67: 0 | J67: 0 | K67: =(C67+D67+E67)*6% -> 33 | L67: 0 | M67: =C67+D67+E67+F67+G67+H67+J67+L67-I67 -> 550
B68: Vitrine 37 | C68: 514.7 | D68: 0 | E68: 0 | F68: 0 | G68: 0 | H68: 0 | I68: 0 | J68: 0 | K68: =(C68+D68+E68)*6% -> 30.882 | L68: 0 | M68: =C68+D68+E68+F68+G68+H68+J68+L68-I68 -> 514.7
B69: Vitrine 38 | C69: 500 | D69: 0 | E69: 0 | F69: 0 | G69: 0 | H69: 0 | I69: 0 | J69: 0 | K69: =(C69+D69+E69)*6% -> 30 | L69: 0 | M69: =C69+D69+E69+F69+G69+H69+J69+L69-I69 -> 500
B70: Vitrine 39 | C70: 358.29 | D70: 0 | E70: 0 | F70: 0 | G70: 0 | H70: 0 | I70: 0 | J70: 0 | K70: =(C70+D70+E70)*6% -> 21.4974 | L70: 0 | M70: =C70+D70+E70+F70+G70+H70+J70+L70-I70 -> 358.29
B71: Vitrine 40 | C71: =277.71 -> 277.71 | D71: 0 | E71: 0 | F71: 0 | G71: 0 | H71: 0 | I71: 0 | J71: 0 | K71: =(C71+D71+E71)*6% -> 16.6626 | L71: 0 | M71: =C71+D71+E71+F71+G71+H71+J71+L71-I71 -> 277.71
B72: Vitrine 41 | C72: 500 | D72: 0 | E72: 0 | F72: 0 | G72: 0 | H72: 0 | I72: 0 | J72: 0 | K72: =(C72+D72+E72)*6% -> 30 | L72: 0 | M72: =C72+D72+E72+F72+G72+H72+J72+L72-I72 -> 500
B73: Vitrine 42 | C73: 360.42 | D73: 0 | E73: 0 | F73: 0 | G73: 0 | H73: 0 | I73: 0 | J73: 0 | K73: =(C73+D73+E73)*6% -> 21.6252 | L73: 0 | M73: =C73+D73+E73+F73+G73+H73+J73+L73-I73 -> 360.42
B74: Vitrine 43 | C74: 600 | D74: 0 | E74: 0 | F74: 0 | G74: 0 | H74: 0 | I74: 0 | J74: 0 | K74: =(C74+D74+E74)*6% -> 36 | L74: 0 | M74: =C74+D74+E74+F74+G74+H74+J74+L74-I74 -> 600
B75: Vitrine 44 | C75: =301.45 -> 301.45 | D75: 0 | E75: 0 | F75: 0 | G75: 0 | H75: 0 | I75: 0 | J75: 0 | K75: =(C75+D75+E75)*6% -> 18.087 | L75: 0 | M75: =C75+D75+E75+F75+G75+H75+J75+L75-I75 -> 301.45
B76: Vitrine 46 | C76: 345.92 | D76: 0 | E76: 0 | F76: 0 | G76: 0 | H76: 0 | I76: 0 | J76: 0 | K76: =(C76+D76+E76)*6% -> 20.7552 | L76: 0 | M76: =C76+D76+E76+F76+G76+H76+J76+L76-I76 -> 345.92
B77: Vitrine 48 | C77: 473.39 | D77: 0 | E77: 0 | F77: 0 | G77: 0 | H77: 0 | I77: 0 | J77: 0 | K77: =(C77+D77+E77)*6% -> 28.4034 | L77: 0 | M77: =C77+D77+E77+F77+G77+H77+J77+L77-I77 -> 473.39
B78: Vitrine 50 | C78: 400 | D78: 0 | E78: 0 | F78: 0 | G78: 0 | H78: 0 | I78: 0 | J78: 0 | K78: =(C78+D78+E78)*6% -> 24 | L78: 0 | M78: =C78+D78+E78+F78+G78+H78+J78+L78-I78 -> 400
B79: Vitrine 52 | C79: =651.91 -> 651.91 | D79: 0 | E79: 0 | F79: 0 | G79: 0 | H79: 0 | I79: 0 | J79: 0 | K79: =(C79+D79+E79)*6% -> 39.1146 | L79: 0 | M79: =C79+D79+E79+F79+G79+H79+J79+L79-I79 -> 651.91
B80: Vitrine 54 | C80: 325.99 | D80: 0 | E80: 0 | F80: 0 | G80: 0 | H80: 0 | I80: 0 | J80: 0 | K80: =(C80+D80+E80)*6% -> 19.5594 | L80: 0 | M80: =C80+D80+E80+F80+G80+H80+J80+L80-I80 -> 325.99
B81: Vitrine 56 | C81: 658.93 | D81: 0 | E81: 0 | F81: 0 | G81: 0 | H81: 0 | I81: 0 | J81: 0 | K81: =(C81+D81+E81)*6% -> 39.5358 | L81: 0 | M81: =C81+D81+E81+F81+G81+H81+J81+L81-I81 -> 658.93
B82: Vitrine 58 | C82: 452.19 | D82: 0 | E82: 0 | F82: 0 | G82: 0 | H82: 0 | I82: 0 | J82: 0 | K82: =(C82+D82+E82)*6% -> 27.1314 | L82: 0 | M82: =C82+D82+E82+F82+G82+H82+J82+L82-I82 -> 452.19
B83: Vitrine 60 | C83: 476.29 | D83: 0 | E83: 0 | F83: 0 | G83: 0 | H83: 0 | I83: 0 | J83: 0 | K83: =(C83+D83+E83)*6% -> 28.5774 | L83: 0 | M83: =C83+D83+E83+F83+G83+H83+J83+L83-I83 -> 476.29
B84: Vitrine 61 | C84: 550 | D84: 0 | E84: 0 | F84: 0 | G84: 0 | H84: 0 | I84: 0 | J84: 0 | K84: =(C84+D84+E84)*6% -> 33 | L84: 0 | M84: =C84+D84+E84+F84+G84+H84+J84+L84-I84 -> 550
B85: Vitrine 63 | C85: 0 | D85: 0 | E85: 0 | F85: 0 | G85: 0 | H85: 0 | I85: 0 | J85: 0 | K85: =(C85+D85+E85)*6% -> 0 | L85: 0 | M85: =C85+D85+E85+F85+G85+H85+J85+L85-I85 -> 0
B86: Quiosque 1 | C86: 0 | D86: 0 | E86: 0 | F86: 0 | G86: 0 | H86: 0 | I86: 0 | J86: 0 | K86: =(C86+D86+E86)*6% -> 0 | L86: 0 | M86: =C86+D86+E86+F86+G86+H86+J86+L86-I86 -> 0
B87: 1ºA | C87: 0 | D87: 0 | E87: 0 | F87: 0 | G87: 0 | H87: 0 | I87: 0 | J87: 0 | K87: =(C87+D87+E87)*6% -> 0 | L87: 0 | M87: =C87+D87+E87+F87+G87+H87+J87+L87-I87 -> 0
B88: 1ºB | C88: 380.39 | D88: 0 | E88: 0 | F88: 368.17 | G88: 66.53 | H88: 0 | I88: 0 | J88: 0 | K88: =(C88+D88+E88)*6% -> 22.8234 | L88: 0 | M88: =C88+D88+E88+F88+G88+H88+J88+L88-I88 -> 815.09
B89: 1ºC | C89: 480.68 | D89: 0 | E89: 0 | F89: 359.67 | G89: 64.99 | H89: 0 | I89: 0 | J89: 0 | K89: =(C89+D89+E89)*6% -> 28.8408 | L89: 0 | M89: =C89+D89+E89+F89+G89+H89+J89+L89-I89 -> 905.34
B90: 1ºD | C90: =451 -> 451 | D90: 0 | E90: 0 | F90: 370.44 | G90: 64.25 | H90: 0 | I90: 0 | J90: 0 | K90: =(C90+D90+E90)*6% -> 27.06 | L90: 0 | M90: =C90+D90+E90+F90+G90+H90+J90+L90-I90 -> 885.69
B91: 1ºE | C91: =541.02 -> 541.02 | D91: 0 | E91: 0 | F91: 437.06 | G91: 75.7 | H91: 0 | I91: 0 | J91: 0 | K91: =(C91+D91+E91)*6% -> 32.4612 | L91: 0 | M91: =C91+D91+E91+F91+G91+H91+J91+L91-I91 -> 1053.78
B92: 1ºF | C92: =566.24-53.12 -> 513.12 | D92: 0 | E92: 0 | F92: 388.63 | G92: 73.2 | H92: 0 | I92: 0 | J92: 0 | K92: =(C92+D92+E92)*6% -> 30.7872 | L92: 0 | M92: =C92+D92+E92+F92+G92+H92+J92+L92-I92 -> 974.95
B93: 1ºG | C93: 438.1 | D93: 0 | E93: 0 | F93: 197.28 | G93: 37.18 | H93: 0 | I93: 0 | J93: 0 | K93: =(C93+D93+E93)*6% -> 26.286 | L93: 0 | M93: =C93+D93+E93+F93+G93+H93+J93+L93-I93 -> 672.56
B94: 1ºH | C94: =351.45 -> 351.45 | D94: 0 | E94: 0 | F94: 208.84 | G94: 39.91 | H94: 0 | I94: 0 | J94: 0 | K94: =(C94+D94+E94)*6% -> 21.087 | L94: 0 | M94: =C94+D94+E94+F94+G94+H94+J94+L94-I94 -> 600.2
B95: 1ºI | C95: 486.23 | D95: 0 | E95: 0 | F95: 390.7 | G95: 74.77 | H95: 0 | I95: 0 | J95: 0 | K95: =(C95+D95+E95)*6% -> 29.1738 | L95: 0 | M95: =C95+D95+E95+F95+G95+H95+J95+L95-I95 -> 951.7
B96: 1ºJ | C96: 481.68 | D96: 58.34 | E96: 0 | F96: 260.04 | G96: 49.69 | H96: 0 | I96: 0 | J96: 0 | K96: =(C96+D96+E96)*6% -> 32.4012 | L96: 0 | M96: =C96+D96+E96+F96+G96+H96+J96+L96-I96 -> 849.75
B97: 1ºK | C97: 0 | D97: 0 | E97: 630 | F97: 0 | G97: 0 | H97: 0 | I97: 0 | J97: 0 | K97: =(C97+D97+E97)*6% -> 37.8 | L97: 0 | M97: =C97+D97+E97+F97+G97+H97+J97+L97-I97 -> 630
B98: 1ºL | C98: 650 | D98: =65+6.5 -> 71.5 | E98: 0 | F98: 0 | G98: 0 | H98: 0 | I98: 0 | J98: 0 | K98: =(C98+D98+E98)*6% -> 43.29 | L98: 0 | M98: =C98+D98+E98+F98+G98+H98+J98+L98-I98 -> 721.5
B99: 1ºM | C99: 384.62 | D99: 0 | E99: 0 | F99: 706.88 | G99: 0 | H99: 0 | I99: 0 | J99: 0 | K99: =(C99+D99+E99)*6% -> 23.0772 | L99: 0 | M99: =C99+D99+E99+F99+G99+H99+J99+L99-I99 -> 1091.5
B100: 2ºA | C100: 557.91 | D100: 0 | E100: 0 | F100: 363.13 | G100: 65.6 | H100: 0 | I100: 0 | J100: 0 | K100: =(C100+D100+E100)*6% -> 33.4746 | L100: 0 | M100: =C100+D100+E100+F100+G100+H100+J100+L100-I100 -> 986.64
B101: 2ºB | C101: =656.96-172.95 -> 484.01 | D101: 0 | E101: 0 | F101: 368.17 | G101: 66.53 | H101: 0 | I101: 0 | J101: 0 | K101: =(C101+D101+E101)*6% -> 29.0406 | L101: 0 | M101: =C101+D101+E101+F101+G101+H101+J101+L101-I101 -> 918.71
B102: 2ºC | C102: =711.42-243.61 -> 467.81 | D102: 0 | E102: 0 | F102: 359.67 | G102: 64.99 | H102: 0 | I102: 0 | J102: 0 | K102: =(C102+D102+E102)*6% -> 28.0686 | L102: 0 | M102: =C102+D102+E102+F102+G102+H102+J102+L102-I102 -> 892.47
B103: 2ºC | C103: 0 | D103: 0 | E103: 0 | F103: 0 | K103: =(C103+D103+E103)*6% -> 0 | M103: =C103+D103+E103+F103+G103+H103+J103+L103-I103 -> 0
B104: 2ºD | C104: 383.08 | D104: 52.14 | E104: 0 | F104: 370.44 | G104: 64.25 | H104: 0 | I104: 0 | J104: 0 | K104: =(C104+D104+E104)*6% -> 26.1132 | L104: 0 | M104: =C104+D104+E104+F104+G104+H104+J104+L104-I104 -> 869.91
B105: 2ºE | C105: 493.7 | D105: 0 | E105: 0 | F105: 437.06 | G105: 75.7 | H105: 0 | I105: 0 | J105: 0 | K105: =(C105+D105+E105)*6% -> 29.622 | L105: 0 | M105: =C105+D105+E105+F105+G105+H105+J105+L105-I105 -> 1006.46
...

Sheet Dist. Receitas
B5: DISTRIBUIÇÃO DE RECEITAS - MAIO/2026
B7: Receitas | N7: ROPSIME C | O7: CAROLINE | P7: THYAGO | Q7: FREDERICO | R7: EDDA | S7: CLAUDINA | T7: VARAM | U7: M. TERESA | V7: HENRIQUE | W7: ADRIANA | X7: CAROLINA | Y7: FKZ | Z7: M. ANTONIO | AA7: JULIANA | AB7: MONIQUE | AC7: VIVIANE | AD7: DENISE | AE7: ROPSIMÉ | AF7: KEUTE | AG7: HALLELUJAH | AH7: ROKE
N8: 0.24 | O8: 0 | P8: 0 | Q8: 0 | R8: 0 | S8: 0.04 | T8: 0.04 | U8: 0.02 | V8: 0.02 | W8: 0 | X8: 0 | Y8: 0.04 | Z8: 0 | AA8: 0.05 | AB8: 0.05 | AC8: 0.05 | AD8: 0.05 | AE8: 0 | AF8: 0.1 | AG8: 0.1 | AH8: 0.2
B9: RECIBO | C9: ALUGUEL | M9: ALUGUEL
B10: Rua Florêncio de Abreu, 60 | C10: 12691.68 | D10: 0 | E10: 0 | F10: 0 | G10: 11802.24 | H10: 0 | I10: 0 | J10: 0 | K10: =(C10+D10+E10)*6% -> 761.5008 | L10: 0 | M10: =C10+D10+E10+F10+G10+H10+J10+L10-I10 -> 24493.92 | N10: =$M$10*N8 -> 5878.5408 | O10: =$M$10*O8 -> 0 | P10: =$M$10*P8 -> 0 | Q10: =$M$10*Q8 -> 0 | R10: =$M$10*R8 -> 0 | S10: =$M$10*S8 -> 979.7568 | T10: =$M$10*T8 -> 979.7568 | U10: =$M$10*U8 -> 489.8784 | ... AH10: =$M$10*AH8 -> 4898.784
B11: Rua Florêncio de Abreu, 66/70/74 | C11: 27461.37 | D11: 0 | E11: 0 | F11: 0 | G11: 11802.24 | H11: 0 | I11: 0 | J11: 0 | K11: =(C11+D11+E11)*6% -> 1647.6822 | L11: 0 | M11: =C11+D11+E11+F11+G11+H11+J11+L11-I11 -> 39263.61 | N11: =$M$11*N8 -> 9423.2664 | O11: =$M$11*O8 -> 0 | P11: =$M$11*P8 -> 0 | Q11: =$M$11*Q8 -> 0 | R11: =$M$11*R8 -> 0 | S11: =$M$11*S8 -> 1570.5444 | T11: =$M$11*T8 -> 1570.5444 | U11: =$M$11*U8 -> 785.2722 | ... AH11: =$M$11*AH8 -> 7852.722
B12: Rua 25 de Março, 669 | C12: =114027.58-9904.5-5281.24-29071.04 -> 69770.8 | D12: 0 | E12: 0 | F12: 0 | G12: 0 | H12: 0 | I12: 0 | J12: 0 | K12: =(C12+D12+E12)*6% -> 4186.248 | L12: 0 | M12: =C12+D12+E12+F12+G12+H12+J12+L12-I12 -> 69770.8 | N12: =$M$12*N8 -> 16744.992 | O12: =$M$12*O8 -> 0 | P12: =$M$12*P8 -> 0 | Q12: =$M$12*Q8 -> 0 | R12: =$M$12*R8 -> 0 | S12: =$M$12*S8 -> 2790.832 | T12: =$M$12*T8 -> 2790.832 | U12: =$M$12*U8 -> 1395.416 | ... AH12: =$M$12*AH8 -> 13954.16
B13: Rua 25 de Março, 661 | C13: =262539.39-97971.06-19679.85 -> 144888.48 | D13: 0 | E13: 0 | F13: 0 | G13: 29268.39 | H13: 0 | I13: =145.51+145.51+695.47+695.47+7817.55+695.49 -> 10195 | J13: 0 | K13: =(C13+D13+E13)*6% -> 8693.3088 | L13: =1051.25+4794.07+1519.59 -> 7364.91 | M13: =C13+D13+E13+F13+G13+H13+J13+L13-I13 -> 171326.78 | N13: =$M$13*$N8-7913.17 -> 33205.257 | O13: =$M$13*O$8 -> 0 | P13: =$M$13*P$8 -> 0 | Q13: =$M$13*Q$8 -> 0 | R13: =$M$13*R$8 -> 0 | S13: =$M$13*S$8-422.44 -> 6430.6312 | T13: =$M$13*T$8-422.44 -> 6430.6312 | U13: =$M$13*U$8 -> 3426.5356 | V13: =$M$13*V$8 -> 3426.5356 | W13: =$M$13*W$8 -> 0 | X13: =$M$13*X$8 -> 0 | Y13: =$M$13*Y$8 -> 6853.0712 | Z13: =$M$13*Z$8 -> 0 | AA13: =$M$13*AA$8-796.97 -> 7769.369 | AB13: =$M$13*AB$8-796.97 -> 7769.369 | AC13: =$M$13*AC$8-796.97 -> 7769.369 | AD13: =$M$13*AD$8 -> 8566.339 | AE13: =$M$13*AE$8 -> 0 | AF13: =$M$13*AF$8 -> 17132.678 | AG13: =$M$13*AG$8 -> 17132.678 | AH13: =$M$13*AH$8 -> 34265.356
B14: Receitas | N14: ROPSIME C | O14: CAROLINE | P14: THYAGO | Q14: FREDERICO | R14: EDDA | S14: CLAUDINA | T14: VARAM | U14: M. TERESA | V14: HENRIQUE | W14: ADRIANA | X14: CAROLINA | Y14: FKZ | Z14: M. ANTONIO | AA14: JULIANA | AB14: MONIQUE | AC14: VIVIANE | AD14: DENISE | AE14: ROPSIMÉ | AF14: KEUTE | AG14: HALLELUJAH | AH14: ROKE
N15: 0.24 | O15: 0.07916667 | P15: 0.06666667 | Q15: 0.07916667 | R15: 0 | S15: 0.0525 | T15: 0.04 | U15: 0.02 | V15: 0.02 | W15: 0.04 | X15: 0 | Y15: 0 | Z15: 0.0125 | AA15: 0 | AB15: 0.05 | AC15: 0.05 | AD15: 0.05 | AE15: 0.2 | AF15: 0 | AG15: 0 | AH15: 0
B16: RECIBO | C16: ALUGUEL | M16: ALUGUEL
B17: Loja 1 | C17: =14443.96-9994.94 -> 4449.02 | D17: 0 | E17: 0 | F17: 3383.25 | G17: 165.26 | H17: 0 | I17: 0 | J17: 0 | K17: =(C17+D17+E17)*6% -> 266.9412 | L17: 0 | M17: =C17+D17+E17+F17+G17+H17+J17+L17-I17 -> 7997.53 | N17: =M17*$N$15 -> 1919.4072 | O17: =M17*$O$15 -> 633.13782 | P17: =M17*$P$15 -> 533.16869 | Q17: =M17*$Q$15 -> 633.13782 | R17: =M17*$R$15 -> 0 | S17: =M17*$S$15 -> 419.87032 | T17: =M17*$T$15 -> 319.9012 | U17: =M17*$U$15 -> 159.9506 | V17: =M17*$U$15 -> 159.9506 | W17: =M17*$W$15 -> 319.9012 | X17: =M17*$X$15 -> 0 | Y17: =N17*$X$15 -> 0 | Z17: =M17*$Z$15 -> 99.969125 | AA17: =M17*$AA$15 -> 0 | AB17: =M17*$AB$15 -> 399.8765 | AC17: =M17*$AC$15 -> 399.8765 | AD17: =M17*$AD$15 -> 399.8765 | AE17: =M17*$AE$15 -> 1599.506 | AF17: =L17*$AH$15 -> 0 | AG17: =M17*$AG$15 -> 0 | AH17: =M17*$AH$15 -> 0
B18: Loja 1A | C18: 1436.57 | D18: 0 | E18: 0 | F18: 419.69 | G18: 29.97 | H18: 0 | I18: 0 | J18: 0 | K18: =(C18+D18+E18)*6% -> 86.1942 | L18: 0 | M18: =C18+D18+E18+F18+G18+H18+J18+L18-I18 -> 1886.23 | N18: =M18*$N$15 -> 452.6952 | O18: =M18*$O$15 -> 149.32655 | P18: =M18*$P$15 -> 125.74867 | Q18: =M18*$Q$15 -> 149.32655 | R18: =M18*$R$15 -> 0 | S18: =M18*$S$15 -> 99.027075 | T18: =M18*$T$15 -> 75.4492 | U18: =M18*$U$15 -> 37.7246 | V18: =M18*$U$15 -> 37.7246 | W18: =M18*$W$15 -> 75.4492 | X18: =M18*$X$15 -> 0 | Y18: =N18*$X$15 -> 0 | Z18: =M18*$Z$15 -> 23.577875 | AA18: =M18*$AA$15 -> 0 | AB18: =M18*$AB$15 -> 94.3115 | AC18: =M18*$AC$15 -> 94.3115 | AD18: =M18*$AD$15 -> 94.3115 | AE18: =M18*$AE$15 -> 377.246 | AF18: =L18*$AH$15 -> 0 | AG18: =M18*$AG$15 -> 0 | AH18: =M18*$AH$15 -> 0
B19: Loja 1B | C19: 1036.03 | D19: 0 | E19: 0 | F19: 269.85 | G19: 19.31 | H19: 0 | I19: 0 | J19: 0 | K19: =(C19+D19+E19)*6% -> 62.1618 | L19: 0 | M19: =C19+D19+E19+F19+G19+H19+J19+L19-I19 -> 1325.19 | N19: =M19*$N$15 -> 318.0456 | O19: =M19*$O$15 -> 104.91088 | P19: =M19*$P$15 -> 88.346004 | Q19: =M19*$Q$15 -> 104.91088 | R19: =M19*$R$15 -> 0 | S19: =M19*$S$15 -> 69.572475 | T19: =M19*$T$15 -> 53.0076 | U19: =M19*$U$15 -> 26.5038 | V19: =M19*$U$15 -> 26.5038 | W19: =M19*$W$15 -> 53.0076 | X19: =M19*$X$15 -> 0 | Y19: =N19*$X$15 -> 0 | Z19: =M19*$Z$15 -> 16.564875 | AA19: =M19*$AA$15 -> 0 | AB19: =M19*$AB$15 -> 66.2595 | AC19: =M19*$AC$15 -> 66.2595 | AD19: =M19*$AD$15 -> 66.2595 | AE19: =M19*$AE$15 -> 265.038 | AF19: =L19*$AH$15 -> 0 | AG19: =M19*$AG$15 -> 0 | AH19: =M19*$AH$15 -> 0
B20: Loja 1C | C20: 0 | D20: 0 | E20: 0 | F20: 0 | G20: 0 | H20: 0 | I20: 0 | J20: 0 | K20: =(C20+D20+E20)*6% -> 0 | L20: 0 | M20: =C20+D20+E20+F20+G20+H20+J20+L20-I20 -> 0 | N20: =M20*$N$15 -> 0 | O20: =M20*$O$15 -> 0 | P20: =M20*$P$15 -> 0 | Q20: =M20*$Q$15 -> 0 | R20: =M20*$R$15 -> 0 | S20: =M20*$S$15 -> 0 | T20: =M20*$T$15 -> 0 | U20: =M20*$U$15 -> 0 | V20: =M20*$U$15 -> 0 | W20: =M20*$W$15 -> 0 | X20: =M20*$X$15 -> 0 | Y20: =N20*$X$15 -> 0 | Z20: =M20*$Z$15 -> 0 | AA20: =M20*$AA$15 -> 0 | AB20: =M20*$AB$15 -> 0 | AC20: =M20*$AC$15 -> 0 | AD20: =M20*$AD$15 -> 0 | AE20: =M20*$AE$15 -> 0 | AF20: =L20*$AH$15 -> 0 | AG20: =M20*$AG$15 -> 0 | AH20: =M20*$AH$15 -> 0
B21: Loja 1C - SS | C21: 0 | D21: 0 | E21: 0 | F21: 0 | G21: 0 | H21: 0 | I21: 0 | J21: 0 | K21: =(C21+D21+E21)*6% -> 0 | L21: 0 | M21: =C21+D21+E21+F21+G21+H21+J21+L21-I21 -> 0 | N21: =M21*$N$15 -> 0 | O21: =M21*$O$15 -> 0 | P21: =M21*$P$15 -> 0 | Q21: =M21*$Q$15 -> 0 | R21: =M21*$R$15 -> 0 | S21: =M21*$S$15 -> 0 | T21: =M21*$T$15 -> 0 | U21: =M21*$U$15 -> 0 | V21: =M21*$U$15 -> 0 | W21: =M21*$W$15 -> 0 | X21: =M21*$X$15 -> 0 | Y21: =N21*$X$15 -> 0 | Z21: =M21*$Z$15 -> 0 | AA21: =M21*$AA$15 -> 0 | AB21: =M21*$AB$15 -> 0 | AC21: =M21*$AC$15 -> 0 | AD21: =M21*$AD$15 -> 0 | AE21: =M21*$AE$15 -> 0 | AF21: =L21*$AH$15 -> 0 | AG21: =M21*$AG$15 -> 0 | AH21: =M21*$AH$15 -> 0
B22: Loja 2A -FRENTE | C22: 1666.77 | D22: 0 | E22: 0 | F22: 1526.98 | G22: 104.47 | H22: 0 | I22: 0 | J22: 0 | K22: =(C22+D22+E22)*6% -> 100.0062 | L22: 209.11 | M22: =C22+D22+E22+F22+G22+H22+J22+L22-I22 -> 3507.33 | N22: =M22*$N$15 -> 841.7592 | O22: =M22*$O$15 -> 277.66364 | P22: =M22*$P$15 -> 233.82201 | Q22: =M22*$Q$15 -> 277.66364 | R22: =M22*$R$15 -> 0 | S22: =M22*$S$15 -> 184.13482 | T22: =M22*$T$15 -> 140.2932 | U22: =M22*$U$15 -> 70.1466 | V22: =M22*$U$15 -> 70.1466 | W22: =M22*$W$15 -> 140.2932 | X22: =M22*$X$15 -> 0 | Y22: =N22*$X$15 -> 0 | Z22: =M22*$Z$15 -> 43.841625 | AA22: =M22*$AA$15 -> 0 | AB22: =M22*$AB$15 -> 175.3665 | AC22: =M22*$AC$15 -> 175.3665 | AD22: =M22*$AD$15 -> 175.3665 | AE22: =M22*$AE$15 -> 701.466 | AF22: =L22*$AH$15 -> 0 | AG22: =M22*$AG$15 -> 0 | AH22: =M22*$AH$15 -> 0
B23: Loja 2-QUADRADA | C23: 1342.42 | D23: 0 | E23: 0 | F23: 1574.98 | G23: 104.47 | H23: 0 | I23: 0 | J23: 0 | K23: =(C23+D23+E23)*6% -> 80.5452 | L23: 0 | M23: =C23+D23+E23+F23+G23+H23+J23+L23-I23 -> 3021.87 | N23: =M23*$N$15 -> 725.2488 | O23: =M23*$O$15 -> 239.23139 | P23: =M23*$P$15 -> 201.45801 | Q23: =M23*$Q$15 -> 239.23139 | R23: =M23*$R$15 -> 0 | S23: =M23*$S$15 -> 158.64817 | T23: =M23*$T$15 -> 120.8748 | U23: =M23*$U$15 -> 60.4374 | V23: =M23*$U$15 -> 60.4374 | W23: =M23*$W$15 -> 120.8748 | X23: =M23*$X$15 -> 0 | Y23: =N23*$X$15 -> 0 | Z23: =M23*$Z$15 -> 37.773375 | AA23: =M23*$AA$15 -> 0 | AB23: =M23*$AB$15 -> 151.0935 | AC23: =M23*$AC$15 -> 151.0935 | AD23: =M23*$AD$15 -> 151.0935 | AE23: =M23*$AE$15 -> 604.374 | AF23: =L23*$AH$15 -> 0 | AG23: =M23*$AG$15 -> 0 | AH23: =M23*$AH$15 -> 0
B24: Loja 2-QUADRADA | C24: 1342.42 | D24: 0 | E24: 0 | F24: 1574.98 | G24: 104.47 | H24: 0 | I24: 0 | J24: 0 | K24: =(C24+D24+E24)*6% -> 80.5452 | L24: 0 | M24: =C24+D24+E24+F24+G24+H24+J24+L24-I24 -> 3021.87 | N24: =M24*$N$15 -> 725.2488 | O24: =M24*$O$15 -> 239.23139 | P24: =M24*$P$15 -> 201.45801 | Q24: =M24*$Q$15 -> 239.23139 | R24: =M24*$R$15 -> 0 | S24: =M24*$S$15 -> 158.64817 | T24: =M24*$T$15 -> 120.8748 | U24: =M24*$U$15 -> 60.4374 | V24: =M24*$U$15 -> 60.4374 | W24: =M24*$W$15 -> 120.8748 | X24: =M24*$X$15 -> 0 | Y24: =N24*$X$15 -> 0 | Z24: =M24*$Z$15 -> 37.773375 | AA24: =M24*$AA$15 -> 0 | AB24: =M24*$AB$15 -> 151.0935 | AC24: =M24*$AC$15 -> 151.0935 | AD24: =M24*$AD$15 -> 151.0935 | AE24: =M24*$AE$15 -> 604.374 | AF24: =L24*$AH$15 -> 0 | AG24: =M24*$AG$15 -> 0 | AH24: =M24*$AH$15 -> 0
B25: Loja 3 | C25: =999.66 -> 999.66 | D25: 0 | E25: 0 | F25: 2062.85 | G25: 134.79 | H25: 0 | I25: 0 | J25: 0 | K25: =(C25+D25+E25)*6% -> 59.9796 | L25: 0 | M25: =C25+D25+E25+F25+G25+H25+J25+L25-I25 -> 3197.3 | N25: =M25*$N$15 -> 767.352 | O25: =M25*$O$15 -> 253.11959 | P25: =M25*$P$15 -> 213.15334 | Q25: =M25*$Q$15 -> 253.11959 | R25: =M25*$R$15 -> 0 | S25: =M25*$S$15 -> 167.85825 | T25: =M25*$T$15 -> 127.892 | U25: =M25*$U$15 -> 63.946 | V25: =M25*$U$15 -> 63.946 | W25: =M25*$W$15 -> 127.892 | X25: =M25*$X$15 -> 0 | Y25: =N25*$X$15 -> 0 | Z25: =M25*$Z$15 -> 39.96625 | AA25: =M25*$AA$15 -> 0 | AB25: =M25*$AB$15 -> 159.865 | AC25: =M25*$AC$15 -> 159.865 | AD25: =M25*$AD$15 -> 159.865 | AE25: =M25*$AE$15 -> 639.46 | AF25: =L25*$AH$15 -> 0 | AG25: =M25*$AG$15 -> 0 | AH25: =M25*$AH$15 -> 0
B26: Loja 4 | C26: =3428.34-2376.65 -> 1051.69 | F26: 2184.84 | G26: 130.1 | K26: =(C26+D26+E26)*6% -> 63.1014 | M26: =C26+D26+E26+F26+G26+H26+J26+L26-I26 -> 3366.63 | N26: =M26*$N$15 -> 807.9912 | O26: =M26*$O$15 -> 266.52489 | P26: =M26*$P$15 -> 224.44201 | Q26: =M26*$Q$15 -> 266.52489 | R26: =M26*$R$15 -> 0 | S26: =M26*$S$15 -> 176.74808 | T26: =M26*$T$15 -> 134.6652 | U26: =M26*$U$15 -> 67.3326 | V26: =M26*$U$15 -> 67.3326 | W26: =M26*$W$15 -> 134.6652 | X26: =M26*$X$15 -> 0 | Y26: =N26*$X$15 -> 0 | Z26: =M26*$Z$15 -> 42.082875 | AA26: =M26*$AA$15 -> 0 | AB26: =M26*$AB$15 -> 168.3315 | AC26: =M26*$AC$15 -> 168.3315 | AD26: =M26*$AD$15 -> 168.3315 | AE26: =M26*$AE$15 -> 673.326 | AF26: =L26*$AH$15 -> 0 | AG26: =M26*$AG$15 -> 0 | AH26: =M26*$AH$15 -> 0
B27: Loja 5 | C27: 0 | D27: 0 | E27: 0 | F27: 0 | G27: 0 | H27: 0 | I27: 0 | J27: 0 | K27: =(C27+D27+E27)*6% -> 0 | L27: 0 | M27: =C27+D27+E27+F27+G27+H27+J27+L27-I27 -> 0 | N27: =M27*$N$15 -> 0 | O27: =M27*$O$15 -> 0 | P27: =M27*$P$15 -> 0 | Q27: =M27*$Q$15 -> 0 | R27: =M27*$R$15 -> 0 | S27: =M27*$S$15 -> 0 | T27: =M27*$T$15 -> 0 | U27: =M27*$U$15 -> 0 | V27: =M27*$U$15 -> 0 | W27: =M27*$W$15 -> 0 | X27: =M27*$X$15 -> 0 | Y27: =N27*$X$15 -> 0 | Z27: =M27*$Z$15 -> 0 | AA27: =M27*$AA$15 -> 0 | AB27: =M27*$AB$15 -> 0 | AC27: =M27*$AC$15 -> 0 | AD27: =M27*$AD$15 -> 0 | AE27: =M27*$AE$15 -> 0 | AF27: =L27*$AH$15 -> 0 | AG27: =M27*$AG$15 -> 0 | AH27: =M27*$AH$15 -> 0
B28: Loja 5A | C28: 1754.25 | D28: 0 | E28: 0 | F28: 424.49 | G28: 0 | H28: 0 | I28: 0 | J28: 0 | K28: =(C28+D28+E28)*6% -> 105.255 | L28: 0 | M28: =C28+D28+E28+F28+G28+H28+J28+L28-I28 -> 2178.74 | N28: =M28*$N$15 -> 522.8976 | O28: =M28*$O$15 -> 172.48359 | P28: =M28*$P$15 -> 145.24934 | Q28: =M28*$Q$15 -> 172.48359 | R28: =M28*$R$15 -> 0 | S28: =M28*$S$15 -> 114.38385 | T28: =M28*$T$15 -> 87.1496 | U28: =M28*$U$15 -> 43.5748 | V28: =M28*$U$15 -> 43.5748 | W28: =M28*$W$15 -> 87.1496 | X28: =M28*$X$15 -> 0 | Y28: =N28*$X$15 -> 0 | Z28: =M28*$Z$15 -> 27.23425 | AA28: =M28*$AA$15 -> 0 | AB28: =M28*$AB$15 -> 108.937 | AC28: =M28*$AC$15 -> 108.937 | AD28: =M28*$AD$15 -> 108.937 | AE28: =M28*$AE$15 -> 435.748 | AF28: =L28*$AH$15 -> 0 | AG28: =M28*$AG$15 -> 0 | AH28: =M28*$AH$15 -> 0
B29: Loja 6/7 | C29: =6275.12-2523.47-467.82-760.25 -> 2523.58 | D29: 0 | E29: 0 | F29: 3018.63 | G29: =81.57+78.84 -> 160.41 | H29: 0 | I29: 0 | J29: 0 | K29: =(C29+D29+E29)*6% -> 151.4148 | L29: 0 | M29: =C29+D29+E29+F29+G29+H29+J29+L29-I29 -> 5702.62 | N29: =M29*$N$15 -> 1368.6288 | O29: =M29*$O$15 -> 451.45744 | P29: =M29*$P$15 -> 380.17469 | Q29: =M29*$Q$15 -> 451.45744 | R29: =M29*$R$15 -> 0 | S29: =M29*$S$15 -> 299.38755 | T29: =M29*$T$15 -> 228.1048 | U29: =M29*$U$15 -> 114.0524 | V29: =M29*$U$15 -> 114.0524 | W29: =M29*$W$15 -> 228.1048 | X29: =M29*$X$15 -> 0 | Y29: =N29*$X$15 -> 0 | Z29: =M29*$Z$15 -> 71.28275 | AA29: =M29*$AA$15 -> 0 | AB29: =M29*$AB$15 -> 285.131 | AC29: =M29*$AC$15 -> 285.131 | AD29: =M29*$AD$15 -> 285.131 | AE29: =M29*$AE$15 -> 1140.524 | AF29: =L29*$AH$15 -> 0 | AG29: =M29*$AG$15 -> 0 | AH29: =M29*$AH$15 -> 0
B30: Loja 7A | C30: 0 | D30: 0 | E30: 0 | F30: 0 | G30: 0 | H30: 0 | I30: 0 | J30: 0 | K30: =(C30+D30+E30)*6% -> 0 | L30: 0 | M30: =C30+D30+E30+F30+G30+H30+J30+L30-I30 -> 0 | N30: =M30*$N$15 -> 0 | O30: =M30*$O$15 -> 0 | P30: =M30*$P$15 -> 0 | Q30: =M30*$Q$15 -> 0 | R30: =M30*$R$15 -> 0 | S30: =M30*$S$15 -> 0 | T30: =M30*$T$15 -> 0 | U30: =M30*$U$15 -> 0 | V30: =M30*$U$15 -> 0 | W30: =M30*$W$15 -> 0 | X30: =M30*$X$15 -> 0 | Y30: =N30*$X$15 -> 0 | Z30: =M30*$Z$15 -> 0 | AA30: =M30*$AA$15 -> 0 | AB30: =M30*$AB$15 -> 0 | AC30: =M30*$AC$15 -> 0 | AD30: =M30*$AD$15 -> 0 | AE30: =M30*$AE$15 -> 0 | AF30: =L30*$AH$15 -> 0 | AG30: =M30*$AG$15 -> 0 | AH30: =M30*$AH$15 -> 0
B31: Loja 8A | C31: 800.24 | D31: 0 | E31: 0 | F31: 666.47 | G31: 21.07 | H31: 0 | I31: 0 | J31: 0 | K31: =(C31+D31+E31)*6% -> 48.0144 | L31: 0 | M31: =C31+D31+E31+F31+G31+H31+J31+L31-I31 -> 1487.78 | N31: =M31*$N$15 -> 357.0672 | O31: =M31*$O$15 -> 117.78259 | P31: =M31*$P$15 -> 99.185338 | Q31: =M31*$Q$15 -> 117.78259 | R31: =M31*$R$15 -> 0 | S31: =M31*$S$15 -> 78.10845 | T31: =M31*$T$15 -> 59.5112 | U31: =M31*$U$15 -> 29.7556 | V31: =M31*$U$15 -> 29.7556 | W31: =M31*$W$15 -> 59.5112 | X31: =M31*$X$15 -> 0 | Y31: =N31*$X$15 -> 0 | Z31: =M31*$Z$15 -> 18.59725 | AA31: =M31*$AA$15 -> 0 | AB31: =M31*$AB$15 -> 74.389 | AC31: =M31*$AC$15 -> 74.389 | AD31: =M31*$AD$15 -> 74.389 | AE31: =M31*$AE$15 -> 297.556 | AF31: =L31*$AH$15 -> 0 | AG31: =M31*$AG$15 -> 0 | AH31: =M31*$AH$15 -> 0
B32: Loja 8A | C32: 0 | D32: 0 | E32: 900 | F32: 0 | G32: 0 | H32: 0 | I32: 0 | J32: 0 | K32: =(C32+D32+E32)*6% -> 54 | L32: 0 | M32: =C32+D32+E32+F32+G32+H32+J32+L32-I32 -> 900 | N32: =M32*$N$15 -> 216 | O32: =M32*$O$15 -> 71.250003 | P32: =M32*$P$15 -> 60.000003 | Q32: =M32*$Q$15 -> 71.250003 | R32: =M32*$R$15 -> 0 | S32: =M32*$S$15 -> 47.25 | T32: =M32*$T$15 -> 36 | U32: =M32*$U$15 -> 18 | V32: =M32*$U$15 -> 18 | W32: =M32*$W$15 -> 36 | X32: =M32*$X$15 -> 0 | Y32: =N32*$X$15 -> 0 | Z32: =M32*$Z$15 -> 11.25 | AA32: =M32*$AA$15 -> 0 | AB32: =M32*$AB$15 -> 45 | AC32: =M32*$AC$15 -> 45 | AD32: =M32*$AD$15 -> 45 | AE32: =M32*$AE$15 -> 180 | AF32: =L32*$AH$15 -> 0 | AG32: =M32*$AG$15 -> 0 | AH32: =M32*$AH$15 -> 0
B33: Loja 8B | C33: =1232.86-378.73 -> 854.13 | D33: 0 | E33: 0 | F33: 435.04 | G33: 13.76 | H33: 0 | I33: 0 | J33: 0 | K33: =(C33+D33+E33)*6% -> 51.2478 | L33: 0 | M33: =C33+D33+E33+F33+G33+H33+J33+L33-I33 -> 1302.93 | N33: =M33*$N$15 -> 312.7032 | O33: =M33*$O$15 -> 103.14863 | P33: =M33*$P$15 -> 86.862004 | Q33: =M33*$Q$15 -> 103.14863 | R33: =M33*$R$15 -> 0 | S33: =M33*$S$15 -> 68.403825 | T33: =M33*$T$15 -> 52.1172 | U33: =M33*$U$15 -> 26.0586 | V33: =M33*$U$15 -> 26.0586 | W33: =M33*$W$15 -> 52.1172 | X33: =M33*$X$15 -> 0 | Y33: =N33*$X$15 -> 0 | Z33: =M33*$Z$15 -> 16.286625 | AA33: =M33*$AA$15 -> 0 | AB33: =M33*$AB$15 -> 65.1465 | AC33: =M33*$AC$15 -> 65.1465 | AD33: =M33*$AD$15 -> 65.1465 | AE33: =M33*$AE$15 -> 260.586 | AF33: =L33*$AH$15 -> 0 | AG33: =M33*$AG$15 -> 0 | AH33: =M33*$AH$15 -> 0
B34: Loja 8-8C | C34: =562.54-89.91 -> 472.63 | E34: 0 | F34: 701.03 | G34: 59.78 | K34: =(C34+D34+E34)*6% -> 28.3578 | L34: 0 | M34: =C34+D34+E34+F34+G34+H34+J34+L34-I34 -> 1233.44 | N34: =M34*$N$15 -> 296.0256 | O34: =M34*$O$15 -> 97.647337 | P34: =M34*$P$15 -> 82.229337 | Q34: =M34*$Q$15 -> 97.647337 | R34: =M34*$R$15 -> 0 | S34: =M34*$S$15 -> 64.7556 | T34: =M34*$T$15 -> 49.3376 | U34: =M34*$U$15 -> 24.6688 | V34: =M34*$U$15 -> 24.6688 | W34: =M34*$W$15 -> 49.3376 | X34: =M34*$X$15 -> 0 | Y34: =N34*$X$15 -> 0 | Z34: =M34*$Z$15 -> 15.418 | AA34: =M34*$AA$15 -> 0 | AB34: =M34*$AB$15 -> 61.672 | AC34: =M34*$AC$15 -> 61.672 | AD34: =M34*$AD$15 -> 61.672 | AE34: =M34*$AE$15 -> 246.688 | AF34: =L34*$AH$15 -> 0 | AG34: =M34*$AG$15 -> 0 | AH34: =M34*$AH$15 -> 0
B35: Loja 8D | C35: 594.74 | D35: 0 | E35: 0 | F35: 1189.92 | G35: 12.77 | H35: 0 | I35: 0 | J35: 0 | K35: =(C35+D35+E35)*6% -> 35.6844 | L35: 0 | M35: =C35+D35+E35+F35+G35+H35+J35+L35-I35 -> 1797.43 | N35: =M35*$N$15 -> 431.3832 | O35: =M35*$O$15 -> 142.29655 | P35: =M35*$P$15 -> 119.82867 | Q35: =M35*$Q$15 -> 142.29655 | R35: =M35*$R$15 -> 0 | S35: =M35*$S$15 -> 94.365075 | T35: =M35*$T$15 -> 71.8972 | U35: =M35*$U$15 -> 35.9486 | V35: =M35*$U$15 -> 35.9486 | W35: =M35*$W$15 -> 71.8972 | X35: =M35*$X$15 -> 0 | Y35: =N35*$X$15 -> 0 | Z35: =M35*$Z$15 -> 22.467875 | AA35: =M35*$AA$15 -> 0 | AB35: =M35*$AB$15 -> 89.8715 | AC35: =M35*$AC$15 -> 89.8715 | AD35: =M35*$AD$15 -> 89.8715 | AE35: =M35*$AE$15 -> 359.486 | AF35: =L35*$AH$15 -> 0 | AG35: =M35*$AG$15 -> 0 | AH35: =M35*$AH$15 -> 0
B36: Loja 9 | C36: =2285.89 -> 2285.89 | D36: 0 | E36: 0 | F36: 2511.34 | G36: 147.84 | H36: 0 | I36: 0 | J36: 0 | K36: =(C36+D36+E36)*6% -> 137.1534 | L36: 0 | M36: =C36+D36+E36+F36+G36+H36+J36+L36-I36 -> 4945.07 | N36: =M36*$N$15 -> 1186.8168 | O36: =M36*$O$15 -> 391.48472 | P36: =M36*$P$15 -> 329.67135 | Q36: =M36*$Q$15 -> 391.48472 | R36: =M36*$R$15 -> 0 | S36: =M36*$S$15 -> 259.61617 | T36: =M36*$T$15 -> 197.8028 | U36: =M36*$U$15 -> 98.9014 | V36: =M36*$U$15 -> 98.9014 | W36: =M36*$W$15 -> 197.8028 | X36: =M36*$X$15 -> 0 | Y36: =N36*$X$15 -> 0 | Z36: =M36*$Z$15 -> 61.813375 | AA36: =M36*$AA$15 -> 0 | AB36: =M36*$AB$15 -> 247.2535 | AC36: =M36*$AC$15 -> 247.2535 | AD36: =M36*$AD$15 -> 247.2535 | AE36: =M36*$AE$15 -> 989.014 | AF36: =L36*$AH$15 -> 0 | AG36: =M36*$AG$15 -> 0 | AH36: =M36*$AH$15 -> 0
B37: Loja 10 | C37: =2260.34 -> 2260.34 | D37: 0 | E37: 0 | F37: 1657.58 | G37: 87.48 | H37: 0 | I37: 0 | J37: 0 | K37: =(C37+D37+E37)*6% -> 135.6204 | L37: 0 | M37: =C37+D37+E37+F37+G37+H37+J37+L37-I37 -> 4005.4 | N37: =M37*$N$15 -> 961.296 | O37: =M37*$O$15 -> 317.09418 | P37: =M37*$P$15 -> 267.02668 | Q37: =M37*$Q$15 -> 317.09418 | R37: =M37*$R$15 -> 0 | S37: =M37*$S$15 -> 210.2835 | T37: =M37*$T$15 -> 160.216 | U37: =M37*$U$15 -> 80.108 | V37: =M37*$U$15 -> 80.108 | W37: =M37*$W$15 -> 160.216 | X37: =M37*$X$15 -> 0 | Y37: =N37*$X$15 -> 0 | Z37: =M37*$Z$15 -> 50.0675 | AA37: =M37*$AA$15 -> 0 | AB37: =M37*$AB$15 -> 200.27 | AC37: =M37*$AC$15 -> 200.27 | AD37: =M37*$AD$15 -> 200.27 | AE37: =M37*$AE$15 -> 801.08 | AF37: =L37*$AH$15 -> 0 | AG37: =M37*$AG$15 -> 0 | AH37: =M37*$AH$15 -> 0
B38: Loja 11 | C38: =2322.36 -> 2322.36 | D38: 0 | E38: 0 | F38: 1575.95 | G38: 83.54 | H38: 0 | I38: 0 | J38: 0 | K38: =(C38+D38+E38)*6% -> 139.3416 | L38: 0 | M38: =C38+D38+E38+F38+G38+H38+J38+L38-I38 -> 3981.85 | N38: =M38*$N$15 -> 955.644 | O38: =M38*$O$15 -> 315.2298 | P38: =M38*$P$15 -> 265.45668 | Q38: =M38*$Q$15 -> 315.2298 | R38: =M38*$R$15 -> 0 | S38: =M38*$S$15 -> 209.04713 | T38: =M38*$T$15 -> 159.274 | U38: =M38*$U$15 -> 79.637 | V38: =M38*$U$15 -> 79.637 | W38: =M38*$W$15 -> 159.274 | X38: =M38*$X$15 -> 0 | Y38: =N38*$X$15 -> 0 | Z38: =M38*$Z$15 -> 49.773125 | AA38: =M38*$AA$15 -> 0 | AB38: =M38*$AB$15 -> 199.0925 | AC38: =M38*$AC$15 -> 199.0925 | AD38: =M38*$AD$15 -> 199.0925 | AE38: =M38*$AE$15 -> 796.37 | AF38: =L38*$AH$15 -> 0 | AG38: =M38*$AG$15 -> 0 | AH38: =M38*$AH$15 -> 0
B39: Loja 12 | C39: 2201.65 | D39: 0 | E39: 0 | F39: 2915.68 | G39: 147.84 | H39: 0 | I39: 0 | J39: 0 | K39: =(C39+D39+E39)*6% -> 132.099 | L39: 0 | M39: =C39+D39+E39+F39+G39+H39+J39+L39-I39 -> 5265.17 | N39: =M39*$N$15 -> 1263.6408 | O39: =M39*$O$15 -> 416.82598 | P39: =M39*$P$15 -> 351.01135 | Q39: =M39*$Q$15 -> 416.82598 | R39: =M39*$R$15 -> 0 | S39: =M39*$S$15 -> 276.42142 | T39: =M39*$T$15 -> 210.6068 | U39: =M39*$U$15 -> 105.3034 | V39: =M39*$U$15 -> 105.3034 | W39: =M39*$W$15 -> 210.6068 | X39: =M39*$X$15 -> 0 | Y39: =N39*$X$15 -> 0 | Z39: =M39*$Z$15 -> 65.814625 | AA39: =M39*$AA$15 -> 0 | AB39: =M39*$AB$15 -> 263.2585 | AC39: =M39*$AC$15 -> 263.2585 | AD39: =M39*$AD$15 -> 263.2585 | AE39: =M39*$AE$15 -> 1053.034 | AF39: =L39*$AH$15 -> 0 | AG39: =M39*$AG$15 -> 0 | AH39: =M39*$AH$15 -> 0
B40: Loja 13 | C40: 1147.54 | D40: 0 | E40: 0 | F40: 1067.93 | G40: 63.27 | H40: 0 | I40: 0 | J40: 0 | K40: =(C40+D40+E40)*6% -> 68.8524 | L40: 0 | M40: =C40+D40+E40+F40+G40+H40+J40+L40-I40 -> 2278.74 | N40: =M40*$N$15 -> 546.8976 | O40: =M40*$O$15 -> 180.40026 | P40: =M40*$P$15 -> 151.91601 | Q40: =M40*$Q$15 -> 180.40026 | R40: =M40*$R$15 -> 0 | S40: =M40*$S$15 -> 119.63385 | T40: =M40*$T$15 -> 91.1496 | U40: =M40*$U$15 -> 45.5748 | V40: =M40*$U$15 -> 45.5748 | W40: =M40*$W$15 -> 91.1496 | X40: =M40*$X$15 -> 0 | Y40: =N40*$X$15 -> 0 | Z40: =M40*$Z$15 -> 28.48425 | AA40: =M40*$AA$15 -> 0 | AB40: =M40*$AB$15 -> 113.937 | AC40: =M40*$AC$15 -> 113.937 | AD40: =M40*$AD$15 -> 113.937 | AE40: =M40*$AE$15 -> 455.748 | AF40: =L40*$AH$15 -> 0 | AG40: =M40*$AG$15 -> 0 | AH40: =M40*$AH$15 -> 0
B41: Loja 13A | C41: =1825.86-156.69 -> 1669.17 | D41: 0 | E41: 0 | F41: 1162.03 | G41: 68.8 | H41: 0 | I41: 0 | J41: 0 | K41: =(C41+D41+E41)*6% -> 100.1502 | L41: 0 | M41: =C41+D41+E41+F41+G41+H41+J41+L41-I41 -> 2900 | N41: =M41*$N$15 -> 696 | O41: =M41*$O$15 -> 229.58334 | P41: =M41*$P$15 -> 193.33334 | Q41: =M41*$Q$15 -> 229.58334 | R41: =M41*$R$15 -> 0 | S41: =M41*$S$15 -> 152.25 | T41: =M41*$T$15 -> 116 | U41: =M41*$U$15 -> 58 | V41: =M41*$U$15 -> 58 | W41: =M41*$W$15 -> 116 | X41: =M41*$X$15 -> 0 | Y41: =N41*$X$15 -> 0 | Z41: =M41*$Z$15 -> 36.25 | AA41: =M41*$AA$15 -> 0 | AB41: =M41*$AB$15 -> 145 | AC41: =M41*$AC$15 -> 145 | AD41: =M41*$AD$15 -> 145 | AE41: =M41*$AE$15 -> 580 | AF41: =L41*$AH$15 -> 0 | AG41: =M41*$AG$15 -> 0 | AH41: =M41*$AH$15 -> 0
B42: Loja 14 | C42: 876.97 | D42: 0 | E42: 0 | F42: 565.64 | G42: 97.34 | H42: 0 | I42: 0 | J42: 0 | K42: =(C42+D42+E42)*6% -> 52.6182 | L42: 0 | M42: =C42+D42+E42+F42+G42+H42+J42+L42-I42 -> 1539.95 | N42: =M42*$N$15 -> 369.588 | O42: =M42*$O$15 -> 121.91271 | P42: =M42*$P$15 -> 102.66334 | Q42: =M42*$Q$15 -> 121.91271 | R42: =M42*$R$15 -> 0 | S42: =M42*$S$15 -> 80.847375 | T42: =M42*$T$15 -> 61.598 | U42: =M42*$U$15 -> 30.799 | V42: =M42*$U$15 -> 30.799 | W42: =M42*$W$15 -> 61.598 | X42: =M42*$X$15 -> 0 | Y42: =N42*$X$15 -> 0 | Z42: =M42*$Z$15 -> 19.249375 | AA42: =M42*$AA$15 -> 0 | AB42: =M42*$AB$15 -> 76.9975 | AC42: =M42*$AC$15 -> 76.9975 | AD42: =M42*$AD$15 -> 76.9975 | AE42: =M42*$AE$15 -> 307.99 | AF42: =L42*$AH$15 -> 0 | AG42: =M42*$AG$15 -> 0 | AH42: =M42*$AH$15 -> 0
B43: Loja 15 | C43: =1848.21 -> 1848.21 | D43: 0 | E43: 0 | F43: 681.87 | G43: 52.56 | H43: 0 | I43: 0 | J43: 0 | K43: =(C43+D43+E43)*6% -> 110.8926 | L43: 0 | M43: =C43+D43+E43+F43+G43+H43+J43+L43-I43 -> 2582.64 | N43: =M43*$N$15 -> 619.8336 | O43: =M43*$O$15 -> 204.45901 | P43: =M43*$P$15 -> 172.17601 | Q43: =M43*$Q$15 -> 204.45901 | R43: =M43*$R$15 -> 0 | S43: =M43*$S$15 -> 135.5886 | T43: =M43*$T$15 -> 103.3056 | U43: =M43*$U$15 -> 51.6528 | V43: =M43*$U$15 -> 51.6528 | W43: =M43*$W$15 -> 103.3056 | X43: =M43*$X$15 -> 0 | Y43: =N43*$X$15 -> 0 | Z43: =M43*$Z$15 -> 32.283 | AA43: =M43*$AA$15 -> 0 | AB43: =M43*$AB$15 -> 129.132 | AC43: =M43*$AC$15 -> 129.132 | AD43: =M43*$AD$15 -> 129.132 | AE43: =M43*$AE$15 -> 516.528 | AF43: =L43*$AH$15 -> 0 | AG43: =M43*$AG$15 -> 0 | AH43: =M43*$AH$15 -> 0
B44: Loja 17 | C44: 1137.96 | D44: =127.3+54.39+109.17 -> 290.86 | E44: 0 | F44: 675.04 | G44: 0 | H44: 0 | I44: 0 | J44: 0 | K44: =(C44+D44+E44)*6% -> 85.7292 | L44: 0 | M44: =C44+D44+E44+F44+G44+H44+J44+L44-I44 -> 2103.86 | N44: =M44*$N$15 -> 504.9264 | O44: =M44*$O$15 -> 166.55559 | P44: =M44*$P$15 -> 140.25734 | Q44: =M44*$Q$15 -> 166.55559 | R44: =M44*$R$15 -> 0 | S44: =M44*$S$15 -> 110.45265 | T44: =M44*$T$15 -> 84.1544 | U44: =M44*$U$15 -> 42.0772 | V44: =M44*$U$15 -> 42.0772 | W44: =M44*$W$15 -> 84.1544 | X44: =M44*$X$15 -> 0 | Y44: =N44*$X$15 -> 0 | Z44: =M44*$Z$15 -> 26.29825 | AA44: =M44*$AA$15 -> 0 | AB44: =M44*$AB$15 -> 105.193 | AC44: =M44*$AC$15 -> 105.193 | AD44: =M44*$AD$15 -> 105.193 | AE44: =M44*$AE$15 -> 420.772 | AF44: =L44*$AH$15 -> 0 | AG44: =M44*$AG$15 -> 0 | AH44: =M44*$AH$15 -> 0
B45: Loja 17A | C45: =1269.15-800 -> 469.15 | D45: 0 | E45: 0 | F45: 508.95 | G45: 21.9 | H45: 0 | I45: 0 | J45: 0 | K45: =(C45+D45+E45)*6% -> 28.149 | L45: 0 | M45: =C45+D45+E45+F45+G45+H45+J45+L45-I45 -> 1000 | N45: =M45*$N$15 -> 240 | O45: =M45*$O$15 -> 79.16667 | P45: =M45*$P$15 -> 66.66667 | Q45: =M45*$Q$15 -> 79.16667 | R45: =M45*$R$15 -> 0 | S45: =M45*$S$15 -> 52.5 | T45: =M45*$T$15 -> 40 | U45: =M45*$U$15 -> 20 | V45: =M45*$U$15 -> 20 | W45: =M45*$W$15 -> 40 | X45: =M45*$X$15 -> 0 | Y45: =N45*$X$15 -> 0 | Z45: =M45*$Z$15 -> 12.5 | AA45: =M45*$AA$15 -> 0 | AB45: =M45*$AB$15 -> 50 | AC45: =M45*$AC$15 -> 50 | AD45: =M45*$AD$15 -> 50 | AE45: =M45*$AE$15 -> 200 | AF45: =L45*$AH$15 -> 0 | AG45: =M45*$AG$15 -> 0 | AH45: =M45*$AH$15 -> 0
B46: Vitrine 1A | C46: 159.56 | D46: 0 | E46: 0 | F46: 0 | G46: 0 | H46: 0 | I46: 0 | J46: 0 | K46: =(C46+D46+E46)*6% -> 9.5736 | L46: 0 | M46: =C46+D46+E46+F46+G46+H46+J46+L46-I46 -> 159.56 | N46: =M46*$N$15 -> 38.2944 | O46: =M46*$O$15 -> 12.631834 | P46: =M46*$P$15 -> 10.637334 | Q46: =M46*$Q$15 -> 12.631834 | R46: =M46*$R$15 -> 0 | S46: =M46*$S$15 -> 8.3769 | T46: =M46*$T$15 -> 6.3824 | U46: =M46*$U$15 -> 3.1912 | V46: =M46*$U$15 -> 3.1912 | W46: =M46*$W$15 -> 6.3824 | X46: =M46*$X$15 -> 0 | Y46: =N46*$X$15 -> 0 | Z46: =M46*$Z$15 -> 1.9945 | AA46: =M46*$AA$15 -> 0 | AB46: =M46*$AB$15 -> 7.978 | AC46: =M46*$AC$15 -> 7.978 | AD46: =M46*$AD$15 -> 7.978 | AE46: =M46*$AE$15 -> 31.912 | AF46: =L46*$AH$15 -> 0 | AG46: =M46*$AG$15 -> 0 | AH46: =M46*$AH$15 -> 0
B47: Vitrine 03 | C47: 324.7 | D47: 0 | E47: 0 | F47: 0 | G47: 0 | H47: 0 | I47: 0 | J47: 0 | K47: =(C47+D47+E47)*6% -> 19.482 | L47: 0 | M47: =C47+D47+E47+F47+G47+H47+J47+L47-I47 -> 324.7 | N47: =M47*$N$15 -> 77.928 | O47: =M47*$O$15 -> 25.705418 | P47: =M47*$P$15 -> 21.646668 | Q47: =M47*$Q$15 -> 25.705418 | R47: =M47*$R$15 -> 0 | S47: =M47*$S$15 -> 17.04675 | T47: =M47*$T$15 -> 12.988 | U47: =M47*$U$15 -> 6.494 | V47: =M47*$U$15 -> 6.494 | W47: =M47*$W$15 -> 12.988 | X47: =M47*$X$15 -> 0 | Y47: =N47*$X$15 -> 0 | Z47: =M47*$Z$15 -> 4.05875 | AA47: =M47*$AA$15 -> 0 | AB47: =M47*$AB$15 -> 16.235 | AC47: =M47*$AC$15 -> 16.235 | AD47: =M47*$AD$15 -> 16.235 | AE47: =M47*$AE$15 -> 64.94 | AF47: =L47*$AH$15 -> 0 | AG47: =M47*$AG$15 -> 0 | AH47: =M47*$AH$15 -> 0
B48: Vitrine 4A | C48: 416.56 | D48: 0 | E48: 0 | F48: 0 | G48: 0 | H48: 0 | I48: 0 | J48: 0 | K48: =(C48+D48+E48)*6% -> 24.9936 | L48: 0 | M48: =C48+D48+E48+F48+G48+H48+J48+L48-I48 -> 416.56 | N48: =M48*$N$15 -> 99.9744 | O48: =M48*$O$15 -> 32.977668 | P48: =M48*$P$15 -> 27.770668 | Q48: =M48*$Q$15 -> 32.977668 | R48: =M48*$R$15 -> 0 | S48: =M48*$S$15 -> 21.8694 | T48: =M48*$T$15 -> 16.6624 | U48: =M48*$U$15 -> 8.3312 | V48: =M48*$U$15 -> 8.3312 | W48: =M48*$W$15 -> 16.6624 | X48: =M48*$X$15 -> 0 | Y48: =N48*$X$15 -> 0 | Z48: =M48*$Z$15 -> 5.207 | AA48: =M48*$AA$15 -> 0 | AB48: =M48*$AB$15 -> 20.828 | AC48: =M48*$AC$15 -> 20.828 | AD48: =M48*$AD$15 -> 20.828 | AE48: =M48*$AE$15 -> 83.312 | AF48: =L48*$AH$15 -> 0 | AG48: =M48*$AG$15 -> 0 | AH48: =M48*$AH$15 -> 0
B49: Vitrine 5A/5B | C49: 336.87 | D49: 0 | E49: 0 | F49: 0 | G49: 0 | H49: 0 | I49: 0 | J49: 0 | K49: =(C49+D49+E49)*6% -> 20.2122 | L49: 0 | M49: =C49+D49+E49+F49+G49+H49+J49+L49-I49 -> 336.87 | N49: =M49*$N$15 -> 80.8488 | O49: =M49*$O$15 -> 26.668876 | P49: =M49*$P$15 -> 22.458001 | Q49: =M49*$Q$15 -> 26.668876 | R49: =M49*$R$15 -> 0 | S49: =M49*$S$15 -> 17.685675 | T49: =M49*$T$15 -> 13.4748 | U49: =M49*$U$15 -> 6.7374 | V49: =M49*$U$15 -> 6.7374 | W49: =M49*$W$15 -> 13.4748 | X49: =M49*$X$15 -> 0 | Y49: =N49*$X$15 -> 0 | Z49: =M49*$Z$15 -> 4.210875 | AA49: =M49*$AA$15 -> 0 | AB49: =M49*$AB$15 -> 16.8435 | AC49: =M49*$AC$15 -> 16.8435 | AD49: =M49*$AD$15 -> 16.8435 | AE49: =M49*$AE$15 -> 67.374 | AF49: =L49*$AH$15 -> 0 | AG49: =M49*$AG$15 -> 0 | AH49: =M49*$AH$15 -> 0
B50: Vitrine 08 | C50: 164.26 | D50: 0 | E50: 0 | F50: 0 | G50: 0 | H50: 0 | I50: 0 | J50: 0 | K50: =(C50+D50+E50)*6% -> 9.8556 | L50: 0 | M50: =C50+D50+E50+F50+G50+H50+J50+L50-I50 -> 164.26 | N50: =M50*$N$15 -> 39.4224 | O50: =M50*$O$15 -> 13.003917 | P50: =M50*$P$15 -> 10.950667 | Q50: =M50*$Q$15 -> 13.003917 | R50: =M50*$R$15 -> 0 | S50: =M50*$S$15 -> 8.62365 | T50: =M50*$T$15 -> 6.5704 | U50: =M50*$U$15 -> 3.2852 | V50: =M50*$U$15 -> 3.2852 | W50: =M50*$W$15 -> 6.5704 | X50: =M50*$X$15 -> 0 | Y50: =N50*$X$15 -> 0 | Z50: =M50*$Z$15 -> 2.05325 | AA50: =M50*$AA$15 -> 0 | AB50: =M50*$AB$15 -> 8.213 | AC50: =M50*$AC$15 -> 8.213 | AD50: =M50*$AD$15 -> 8.213 | AE50: =M50*$AE$15 -> 32.852 | AF50: =L50*$AH$15 -> 0 | AG50: =M50*$AG$15 -> 0 | AH50: =M50*$AH$15 -> 0
B51: Vitrine 10 | C51: 230.18 | D51: 0 | E51: 0 | F51: 0 | G51: 0 | H51: 0 | I51: 0 | J51: 0 | K51: =(C51+D51+E51)*6% -> 13.8108 | L51: 0 | M51: =C51+D51+E51+F51+G51+H51+J51+L51-I51 -> 230.18 | N51: =M51*$N$15 -> 55.2432 | O51: =M51*$O$15 -> 18.222584 | P51: =M51*$P$15 -> 15.345334 | Q51: =M51*$Q$15 -> 18.222584 | R51: =M51*$R$15 -> 0 | S51: =M51*$S$15 -> 12.08445 | T51: =M51*$T$15 -> 9.2072 | U51: =M51*$U$15 -> 4.6036 | V51: =M51*$U$15 -> 4.6036 | W51: =M51*$W$15 -> 9.2072 | X51: =M51*$X$15 -> 0 | Y51: =N51*$X$15 -> 0 | Z51: =M51*$Z$15 -> 2.87725 | AA51: =M51*$AA$15 -> 0 | AB51: =M51*$AB$15 -> 11.509 | AC51: =M51*$AC$15 -> 11.509 | AD51: =M51*$AD$15 -> 11.509 | AE51: =M51*$AE$15 -> 46.036 | AF51: =L51*$AH$15 -> 0 | AG51: =M51*$AG$15 -> 0 | AH51: =M51*$AH$15 -> 0
B52: Vitrine 7A/7B | C52: 336.87 | D52: 0 | E52: 0 | F52: 0 | G52: 0 | H52: 0 | I52: 0 | J52: 0 | K52: =(C52+D52+E52)*6% -> 20.2122 | L52: 0 | M52: =C52+D52+E52+F52+G52+H52+J52+L52-I52 -> 336.87 | N52: =M52*$N$15 -> 80.8488 | O52: =M52*$O$15 -> 26.668876 | P52: =M52*$P$15 -> 22.458001 | Q52: =M52*$Q$15 -> 26.668876 | R52: =M52*$R$15 -> 0 | S52: =M52*$S$15 -> 17.685675 | T52: =M52*$T$15 -> 13.4748 | U52: =M52*$U$15 -> 6.7374 | V52: =M52*$U$15 -> 6.7374 | W52: =M52*$W$15 -> 13.4748 | X52: =M52*$X$15 -> 0 | Y52: =N52*$X$15 -> 0 | Z52: =M52*$Z$15 -> 4.210875 | AA52: =M52*$AA$15 -> 0 | AB52: =M52*$AB$15 -> 16.8435 | AC52: =M52*$AC$15 -> 16.8435 | AD52: =M52*$AD$15 -> 16.8435 | AE52: =M52*$AE$15 -> 67.374 | AF52: =L52*$AH$15 -> 0 | AG52: =M52*$AG$15 -> 0 | AH52: =M52*$AH$15 -> 0
B53: Vitrine 9A/9B | C53: 531.87 | D53: 0 | E53: 0 | F53: 0 | G53: 0 | H53: 0 | I53: 0 | J53: 0 | K53: =(C53+D53+E53)*6% -> 31.9122 | L53: 0 | M53: =C53+D53+E53+F53+G53+H53+J53+L53-I53 -> 531.87 | N53: =M53*$N$15 -> 127.6488 | O53: =M53*$O$15 -> 42.106377 | P53: =M53*$P$15 -> 35.458002 | Q53: =M53*$Q$15 -> 42.106377 | R53: =M53*$R$15 -> 0 | S53: =M53*$S$15 -> 27.923175 | T53: =M53*$T$15 -> 21.2748 | U53: =M53*$U$15 -> 10.6374 | V53: =M53*$U$15 -> 10.6374 | W53: =M53*$W$15 -> 21.2748 | X53: =M53*$X$15 -> 0 | Y53: =N53*$X$15 -> 0 | Z53: =M53*$Z$15 -> 6.648375 | AA53: =M53*$AA$15 -> 0 | AB53: =M53*$AB$15 -> 26.5935 | AC53: =M53*$AC$15 -> 26.5935 | AD53: =M53*$AD$15 -> 26.5935 | AE53: =M53*$AE$15 -> 106.374 | AF53: =L53*$AH$15 -> 0 | AG53: =M53*$AG$15 -> 0 | AH53: =M53*$AH$15 -> 0
B54: Vitrine 11A/11B | C54: 0 | D54: 0 | E54: 0 | F54: 0 | G54: 0 | H54: 0 | I54: 0 | J54: 0 | K54: 0 | L54: 0 | M54: =C54+D54+E54+F54+G54+H54+J54+L54-I54 -> 0 | N54: =M54*$N$15 -> 0 | O54: =M54*$O$15 -> 0 | P54: =M54*$P$15 -> 0 | Q54: =M54*$Q$15 -> 0 | R54: =M54*$R$15 -> 0 | S54: =M54*$S$15 -> 0 | T54: =M54*$T$15 -> 0 | U54: =M54*$U$15 -> 0 | V54: =M54*$U$15 -> 0 | W54: =M54*$W$15 -> 0 | X54: =M54*$X$15 -> 0 | Y54: =N54*$X$15 -> 0 | Z54: =M54*$Z$15 -> 0 | AA54: =M54*$AA$15 -> 0 | AB54: =M54*$AB$15 -> 0 | AC54: =M54*$AC$15 -> 0 | AD54: =M54*$AD$15 -> 0 | AE54: =M54*$AE$15 -> 0 | AF54: =L54*$AH$15 -> 0 | AG54: =M54*$AG$15 -> 0 | AH54: =M54*$AH$15 -> 0
B55: Vitrine 12 | C55: 473.11 | D55: 0 | E55: 0 | F55: 0 | G55: 0 | H55: 0 | I55: 0 | J55: 0 | K55: =(C55+D55+E55)*6% -> 28.3866 | L55: 0 | M55: =C55+D55+E55+F55+G55+H55+J55+L55-I55 -> 473.11 | N55: =M55*$N$15 -> 113.5464 | O55: =M55*$O$15 -> 37.454543 | P55: =M55*$P$15 -> 31.540668 | Q55: =M55*$Q$15 -> 37.454543 | R55: =M55*$R$15 -> 0 | S55: =M55*$S$15 -> 24.838275 | T55: =M55*$T$15 -> 18.9244 | U55: =M55*$U$15 -> 9.4622 | V55: =M55*$U$15 -> 9.4622 | W55: =M55*$W$15 -> 18.9244 | X55: =M55*$X$15 -> 0 | Y55: =N55*$X$15 -> 0 | Z55: =M55*$Z$15 -> 5.913875 | AA55: =M55*$AA$15 -> 0 | AB55: =M55*$AB$15 -> 23.6555 | AC55: =M55*$AC$15 -> 23.6555 | AD55: =M55*$AD$15 -> 23.6555 | AE55: =M55*$AE$15 -> 94.622 | AF55: =L55*$AH$15 -> 0 | AG55: =M55*$AG$15 -> 0 | AH55: =M55*$AH$15 -> 0
B56: Vitrine 13A/13B | C56: 667.66 | D56: 0 | E56: 0 | F56: 0 | G56: 0 | H56: 0 | I56: 0 | J56: 0 | K56: =(C56+D56+E56)*6% -> 40.0596 | L56: 0 | M56: =C56+D56+E56+F56+G56+H56+J56+L56-I56 -> 667.66 | N56: =M56*$N$15 -> 160.2384 | O56: =M56*$O$15 -> 52.856419 | P56: =M56*$P$15 -> 44.510669 | Q56: =M56*$Q$15 -> 52.856419 | R56: =M56*$R$15 -> 0 | S56: =M56*$S$15 -> 35.05215 | T56: =M56*$T$15 -> 26.7064 | U56: =M56*$U$15 -> 13.3532 | V56: =M56*$U$15 -> 13.3532 | W56: =M56*$W$15 -> 26.7064 | X56: =M56*$X$15 -> 0 | Y56: =N56*$X$15 -> 0 | Z56: =M56*$Z$15 -> 8.34575 | AA56: =M56*$AA$15 -> 0 | AB56: =M56*$AB$15 -> 33.383 | AC56: =M56*$AC$15 -> 33.383 | AD56: =M56*$AD$15 -> 33.383 | AE56: =M56*$AE$15 -> 133.532 | AF56: =L56*$AH$15 -> 0 | AG56: =M56*$AG$15 -> 0 | AH56: =M56*$AH$15 -> 0
B57: Vitrine 15/17 | C57: 409.05 | D57: 0 | E57: 0 | F57: 0 | G57: 0 | H57: 0 | I57: 0 | J57: 0 | K57: =(C57+D57+E57)*6% -> 24.543 | L57: 0 | M57: =C57+D57+E57+F57+G57+H57+J57+L57-I57 -> 409.05 | N57: =M57*$N$15 -> 98.172 | O57: =M57*$O$15 -> 32.383126 | P57: =M57*$P$15 -> 27.270001 | Q57: =M57*$Q$15 -> 32.383126 | R57: =M57*$R$15 -> 0 | S57: =M57*$S$15 -> 21.475125 | T57: =M57*$T$15 -> 16.362 | U57: =M57*$U$15 -> 8.181 | V57: =M57*$U$15 -> 8.181 | W57: =M57*$W$15 -> 16.362 | X57: =M57*$X$15 -> 0 | Y57: =N57*$X$15 -> 0 | Z57: =M57*$Z$15 -> 5.113125 | AA57: =M57*$AA$15 -> 0 | AB57: =M57*$AB$15 -> 20.4525 | AC57: =M57*$AC$15 -> 20.4525 | AD57: =M57*$AD$15 -> 20.4525 | AE57: =M57*$AE$15 -> 81.81 | AF57: =L57*$AH$15 -> 0 | AG57: =M57*$AG$15 -> 0 | AH57: =M57*$AH$15 -> 0
B58: Vitrine 18 | C58: 200 | K58: =(C58+D58+E58)*6% -> 12 | M58: =C58+D58+E58+F58+G58+H58+J58+L58-I58 -> 200 | N58: =M58*$N$15 -> 48 | O58: =M58*$O$15 -> 15.833334 | P58: =M58*$P$15 -> 13.333334 | Q58: =M58*$Q$15 -> 15.833334 | R58: =M58*$R$15 -> 0 | S58: =M58*$S$15 -> 10.5 | T58: =M58*$T$15 -> 8 | U58: =M58*$U$15 -> 4 | V58: =M58*$U$15 -> 4 | W58: =M58*$W$15 -> 8 | X58: =M58*$X$15 -> 0 | Y58: =N58*$X$15 -> 0 | Z58: =M58*$Z$15 -> 2.5 | AA58: =M58*$AA$15 -> 0 | AB58: =M58*$AB$15 -> 10 | AC58: =M58*$AC$15 -> 10 | AD58: =M58*$AD$15 -> 10 | AE58: =M58*$AE$15 -> 40 | AF58: =L58*$AH$15 -> 0 | AG58: =M58*$AG$15 -> 0 | AH58: =M58*$AH$15 -> 0
B59: Vitrine 19/21/23/25 | C59: 737.53 | D59: 0 | E59: 0 | F59: 0 | G59: 0 | H59: 0 | I59: 0 | J59: 0 | K59: =(C59+D59+E59)*6% -> 44.2518 | L59: 0 | M59: =C59+D59+E59+F59+G59+H59+J59+L59-I59 -> 737.53 | N59: =M59*$N$15 -> 177.0072 | O59: =M59*$O$15 -> 58.387794 | P59: =M59*$P$15 -> 49.168669 | Q59: =M59*$Q$15 -> 58.387794 | R59: =M59*$R$15 -> 0 | S59: =M59*$S$15 -> 38.720325 | T59: =M59*$T$15 -> 29.5012 | U59: =M59*$U$15 -> 14.7506 | V59: =M59*$U$15 -> 14.7506 | W59: =M59*$W$15 -> 29.5012 | X59: =M59*$X$15 -> 0 | Y59: =N59*$X$15 -> 0 | Z59: =M59*$Z$15 -> 9.219125 | AA59: =M59*$AA$15 -> 0 | AB59: =M59*$AB$15 -> 36.8765 | AC59: =M59*$AC$15 -> 36.8765 | AD59: =M59*$AD$15 -> 36.8765 | AE59: =M59*$AE$15 -> 147.506 | AF59: =L59*$AH$15 -> 0 | AG59: =M59*$AG$15 -> 0 | AH59: =M59*$AH$15 -> 0
B60: Vitrine 20 | C60: 0 | D60: 0 | K60: =(C60+D60+E60)*6% -> 0 | M60: =C60+D60+E60+F60+G60+H60+J60+L60-I60 -> 0 | N60: =M60*$N$15 -> 0 | O60: =M60*$O$15 -> 0 | P60: =M60*$P$15 -> 0 | Q60: =M60*$Q$15 -> 0 | R60: =M60*$R$15 -> 0 | S60: =M60*$S$15 -> 0 | T60: =M60*$T$15 -> 0 | U60: =M60*$U$15 -> 0 | V60: =M60*$U$15 -> 0 | W60: =M60*$W$15 -> 0 | X60: =M60*$X$15 -> 0 | Y60: =N60*$X$15 -> 0 | Z60: =M60*$Z$15 -> 0 | AA60: =M60*$AA$15 -> 0 | AB60: =M60*$AB$15 -> 0 | AC60: =M60*$AC$15 -> 0 | AD60: =M60*$AD$15 -> 0 | AE60: =M60*$AE$15 -> 0 | AF60: =L60*$AH$15 -> 0 | AG60: =M60*$AG$15 -> 0 | AH60: =M60*$AH$15 -> 0
B61: Vitrine 22/24 | C61: 505.31 | D61: 0 | E61: 0 | F61: 0 | G61: 0 | H61: 0 | I61: 0 | J61: 0 | K61: =(C61+D61+E61)*6% -> 30.3186 | L61: 0 | M61: =C61+D61+E61+F61+G61+H61+J61+L61-I61 -> 505.31 | N61: =M61*$N$15 -> 121.2744 | O61: =M61*$O$15 -> 40.00371 | P61: =M61*$P$15 -> 33.687335 | Q61: =M61*$Q$15 -> 40.00371 | R61: =M61*$R$15 -> 0 | S61: =M61*$S$15 -> 26.528775 | T61: =M61*$T$15 -> 20.2124 | U61: =M61*$U$15 -> 10.1062 | V61: =M61*$U$15 -> 10.1062 | W61: =M61*$W$15 -> 20.2124 | X61: =M61*$X$15 -> 0 | Y61: =N61*$X$15 -> 0 | Z61: =M61*$Z$15 -> 6.316375 | AA61: =M61*$AA$15 -> 0 | AB61: =M61*$AB$15 -> 25.2655 | AC61: =M61*$AC$15 -> 25.2655 | AD61: =M61*$AD$15 -> 25.2655 | AE61: =M61*$AE$15 -> 101.062 | AF61: =L61*$AH$15 -> 0 | AG61: =M61*$AG$15 -> 0 | AH61: =M61*$AH$15 -> 0
B62: Vitrine 26/28 | C62: =525.68 -> 525.68 | D62: 0 | E62: 0 | F62: 0 | G62: 0 | H62: 0 | I62: 0 | J62: 0 | K62: =(C62+D62+E62)*6% -> 31.5408 | L62: 0 | M62: =C62+D62+E62+F62+G62+H62+J62+L62-I62 -> 525.68 | N62: =M62*$N$15 -> 126.1632 | O62: =M62*$O$15 -> 41.616335 | P62: =M62*$P$15 -> 35.045335 | Q62: =M62*$Q$15 -> 41.616335 | R62: =M62*$R$15 -> 0 | S62: =M62*$S$15 -> 27.5982 | T62: =M62*$T$15 -> 21.0272 | U62: =M62*$U$15 -> 10.5136 | V62: =M62*$U$15 -> 10.5136 | W62: =M62*$W$15 -> 21.0272 | X62: =M62*$X$15 -> 0 | Y62: =N62*$X$15 -> 0 | Z62: =M62*$Z$15 -> 6.571 | AA62: =M62*$AA$15 -> 0 | AB62: =M62*$AB$15 -> 26.284 | AC62: =M62*$AC$15 -> 26.284 | AD62: =M62*$AD$15 -> 26.284 | AE62: =M62*$AE$15 -> 105.136 | AF62: =L62*$AH$15 -> 0 | AG62: =M62*$AG$15 -> 0 | AH62: =M62*$AH$15 -> 0
B63: Vitrine 27 | C63: 100 | D63: 0 | E63: 0 | F63: 0 | G63: 0 | H63: 0 | I63: 0 | J63: 0 | K63: =(C63+D63+E63)*6% -> 6 | L63: 0 | M63: =C63+D63+E63+F63+G63+H63+J63+L63-I63 -> 100 | N63: =M63*$N$15 -> 24 | O63: =M63*$O$15 -> 7.916667 | P63: =M63*$P$15 -> 6.666667 | Q63: =M63*$Q$15 -> 7.916667 | R63: =M63*$R$15 -> 0 | S63: =M63*$S$15 -> 5.25 | T63: =M63*$T$15 -> 4 | U63: =M63*$U$15 -> 2 | V63: =M63*$U$15 -> 2 | W63: =M63*$W$15 -> 4 | X63: =M63*$X$15 -> 0 | Y63: =N63*$X$15 -> 0 | Z63: =M63*$Z$15 -> 1.25 | AA63: =M63*$AA$15 -> 0 | AB63: =M63*$AB$15 -> 5 | AC63: =M63*$AC$15 -> 5 | AD63: =M63*$AD$15 -> 5 | AE63: =M63*$AE$15 -> 20 | AF63: =L63*$AH$15 -> 0 | AG63: =M63*$AG$15 -> 0 | AH63: =M63*$AH$15 -> 0
B64: Vitrine 29 | C64: 490.24 | D64: 0 | E64: 0 | F64: 0 | G64: 0 | H64: 0 | I64: 0 | J64: 0 | K64: =(C64+D64+E64)*6% -> 29.4144 | L64: 0 | M64: =C64+D64+E64+F64+G64+H64+J64+L64-I64 -> 490.24 | N64: =M64*$N$15 -> 117.6576 | O64: =M64*$O$15 -> 38.810668 | P64: =M64*$P$15 -> 32.682668 | Q64: =M64*$Q$15 -> 38.810668 | R64: =M64*$R$15 -> 0 | S64: =M64*$S$15 -> 25.7376 | T64: =M64*$T$15 -> 19.6096 | U64: =M64*$U$15 -> 9.8048 | V64: =M64*$U$15 -> 9.8048 | W64: =M64*$W$15 -> 19.6096 | X64: =M64*$X$15 -> 0 | Y64: =N64*$X$15 -> 0 | Z64: =M64*$Z$15 -> 6.128 | AA64: =M64*$AA$15 -> 0 | AB64: =M64*$AB$15 -> 24.512 | AC64: =M64*$AC$15 -> 24.512 | AD64: =M64*$AD$15 -> 24.512 | AE64: =M64*$AE$15 -> 98.048 | AF64: =L64*$AH$15 -> 0 | AG64: =M64*$AG$15 -> 0 | AH64: =M64*$AH$15 -> 0
B65: Vitrine 30 | C65: 341.48 | D65: 0 | E65: 0 | F65: 0 | G65: 0 | H65: 0 | I65: 0 | J65: 0 | K65: =(C65+D65+E65)*6% -> 20.4888 | L65: 0 | M65: =C65+D65+E65+F65+G65+H65+J65+L65-I65 -> 341.48 | N65: =M65*$N$15 -> 81.9552 | O65: =M65*$O$15 -> 27.033834 | P65: =M65*$P$15 -> 22.765334 | Q65: =M65*$Q$15 -> 27.033834 | R65: =M65*$R$15 -> 0 | S65: =M65*$S$15 -> 17.9277 | T65: =M65*$T$15 -> 13.6592 | U65: =M65*$U$15 -> 6.8296 | V65: =M65*$U$15 -> 6.8296 | W65: =M65*$W$15 -> 13.6592 | X65: =M65*$X$15 -> 0 | Y65: =N65*$X$15 -> 0 | Z65: =M65*$Z$15 -> 4.2685 | AA65: =M65*$AA$15 -> 0 | AB65: =M65*$AB$15 -> 17.074 | AC65: =M65*$AC$15 -> 17.074 | AD65: =M65*$AD$15 -> 17.074 | AE65: =M65*$AE$15 -> 68.296 | AF65: =L65*$AH$15 -> 0 | AG65: =M65*$AG$15 -> 0 | AH65: =M65*$AH$15 -> 0
B66: Vitrine 31 | C66: 343.76 | D66: 0 | E66: 0 | F66: 0 | G66: 0 | H66: 0 | I66: 0 | J66: 0 | K66: =(C66+D66+E66)*6% -> 20.6256 | L66: 0 | M66: =C66+D66+E66+F66+G66+H66+J66+L66-I66 -> 343.76 | N66: =M66*$N$15 -> 82.5024 | O66: =M66*$O$15 -> 27.214334 | P66: =M66*$P$15 -> 22.917334 | Q66: =M66*$Q$15 -> 27.214334 | R66: =M66*$R$15 -> 0 | S66: =M66*$S$15 -> 18.0474 | T66: =M66*$T$15 -> 13.7504 | U66: =M66*$U$15 -> 6.8752 | V66: =M66*$U$15 -> 6.8752 | W66: =M66*$W$15 -> 13.7504 | X66: =M66*$X$15 -> 0 | Y66: =N66*$X$15 -> 0 | Z66: =M66*$Z$15 -> 4.297 | AA66: =M66*$AA$15 -> 0 | AB66: =M66*$AB$15 -> 17.188 | AC66: =M66*$AC$15 -> 17.188 | AD66: =M66*$AD$15 -> 17.188 | AE66: =M66*$AE$15 -> 68.752 | AF66: =L66*$AH$15 -> 0 | AG66: =M66*$AG$15 -> 0 | AH66: =M66*$AH$15 -> 0
B67: Vitrine 31 | C67: 343.76 | D67: =34.38+3.44 -> 37.82 | E67: 0 | F67: 0 | G67: 0 | H67: 0 | I67: 0 | J67: 0 | K67: =(C67+D67+E67)*6% -> 22.8948 | L67: 0 | M67: =C67+D67+E67+F67+G67+H67+J67+L67-I67 -> 381.58 | N67: =M67*$N$15 -> 91.5792 | O67: =M67*$O$15 -> 30.208418 | P67: =M67*$P$15 -> 25.438668 | Q67: =M67*$Q$15 -> 30.208418 | R67: =M67*$R$15 -> 0 | S67: =M67*$S$15 -> 20.03295 | T67: =M67*$T$15 -> 15.2632 | U67: =M67*$U$15 -> 7.6316 | V67: =M67*$U$15 -> 7.6316 | W67: =M67*$W$15 -> 15.2632 | X67: =M67*$X$15 -> 0 | Y67: =N67*$X$15 -> 0 | Z67: =M67*$Z$15 -> 4.76975 | AA67: =M67*$AA$15 -> 0 | AB67: =M67*$AB$15 -> 19.079 | AC67: =M67*$AC$15 -> 19.079 | AD67: =M67*$AD$15 -> 19.079 | AE67: =M67*$AE$15 -> 76.316 | AF67: =L67*$AH$15 -> 0 | AG67: =M67*$AG$15 -> 0 | AH67: =M67*$AH$15 -> 0
B68: Vitrine 32 | C68: =488.99-209.69 -> 279.3 | D68: 0 | E68: 0 | F68: 0 | G68: 0 | H68: 0 | I68: 0 | J68: 0 | K68: =(C68+D68+E68)*6% -> 16.758 | L68: 0 | M68: =C68+D68+E68+F68+G68+H68+J68+L68-I68 -> 279.3 | N68: =M68*$N$15 -> 67.032 | O68: =M68*$O$15 -> 22.111251 | P68: =M68*$P$15 -> 18.620001 | Q68: =M68*$Q$15 -> 22.111251 | R68: =M68*$R$15 -> 0 | S68: =M68*$S$15 -> 14.66325 | T68: =M68*$T$15 -> 11.172 | U68: =M68*$U$15 -> 5.586 | V68: =M68*$U$15 -> 5.586 | W68: =M68*$W$15 -> 11.172 | X68: =M68*$X$15 -> 0 | Y68: =N68*$X$15 -> 0 | Z68: =M68*$Z$15 -> 3.49125 | AA68: =M68*$AA$15 -> 0 | AB68: =M68*$AB$15 -> 13.965 | AC68: =M68*$AC$15 -> 13.965 | AD68: =M68*$AD$15 -> 13.965 | AE68: =M68*$AE$15 -> 55.86 | AF68: =L68*$AH$15 -> 0 | AG68: =M68*$AG$15 -> 0 | AH68: =M68*$AH$15 -> 0
B69: Vitrine 33 | C69: 500 | D69: 0 | E69: 0 | F69: 0 | G69: 0 | H69: 0 | I69: 0 | J69: 0 | K69: =(C69+D69+E69)*6% -> 30 | L69: 0 | M69: =C69+D69+E69+F69+G69+H69+J69+L69-I69 -> 500 | N69: =M69*$N$15 -> 120 | O69: =M69*$O$15 -> 39.583335 | P69: =M69*$P$15 -> 33.333335 | Q69: =M69*$Q$15 -> 39.583335 | R69: =M69*$R$15 -> 0 | S69: =M69*$S$15 -> 26.25 | T69: =M69*$T$15 -> 20 | U69: =M69*$U$15 -> 10 | V69: =M69*$U$15 -> 10 | W69: =M69*$W$15 -> 20 | X69: =M69*$X$15 -> 0 | Y69: =N69*$X$15 -> 0 | Z69: =M69*$Z$15 -> 6.25 | AA69: =M69*$AA$15 -> 0 | AB69: =M69*$AB$15 -> 25 | AC69: =M69*$AC$15 -> 25 | AD69: =M69*$AD$15 -> 25 | AE69: =M69*$AE$15 -> 100 | AF69: =L69*$AH$15 -> 0 | AG69: =M69*$AG$15 -> 0 | AH69: =M69*$AH$15 -> 0
B70: Vitrine 34 | C70: 592.77 | D70: 0 | E70: 0 | F70: 0 | G70: 0 | H70: 0 | I70: 0 | J70: 0 | K70: =(C70+D70+E70)*6% -> 35.5662 | L70: 0 | M70: =C70+D70+E70+F70+G70+H70+J70+L70-I70 -> 592.77 | N70: =M70*$N$15 -> 142.2648 | O70: =M70*$O$15 -> 46.927627 | P70: =M70*$P$15 -> 39.518002 | Q70: =M70*$Q$15 -> 46.927627 | R70: =M70*$R$15 -> 0 | S70: =M70*$S$15 -> 31.120425 | T70: =M70*$T$15 -> 23.7108 | U70: =M70*$U$15 -> 11.8554 | V70: =M70*$U$15 -> 11.8554 | W70: =M70*$W$15 -> 23.7108 | X70: =M70*$X$15 -> 0 | Y70: =N70*$X$15 -> 0 | Z70: =M70*$Z$15 -> 7.409625 | AA70: =M70*$AA$15 -> 0 | AB70: =M70*$AB$15 -> 29.6385 | AC70: =M70*$AC$15 -> 29.6385 | AD70: =M70*$AD$15 -> 29.6385 | AE70: =M70*$AE$15 -> 118.554 | AF70: =L70*$AH$15 -> 0 | AG70: =M70*$AG$15 -> 0 | AH70: =M70*$AH$15 -> 0
B71: Vitrine 35 | C71: 550 | D71: 0 | E71: 0 | F71: 0 | G71: 0 | H71: 0 | I71: 0 | J71: 0 | K71: =(C71+D71+E71)*6% -> 33 | L71: 0 | M71: =C71+D71+E71+F71+G71+H71+J71+L71-I71 -> 550 | N71: =M71*$N$15 -> 132 | O71: =M71*$O$15 -> 43.541669 | P71: =M71*$P$15 -> 36.666669 | Q71: =M71*$Q$15 -> 43.541669 | R71: =M71*$R$15 -> 0 | S71: =M71*$S$15 -> 28.875 | T71: =M71*$T$15 -> 22 | U71: =M71*$U$15 -> 11 | V71: =M71*$U$15 -> 11 | W71: =M71*$W$15 -> 22 | X71: =M71*$X$15 -> 0 | Y71: =N71*$X$15 -> 0 | Z71: =M71*$Z$15 -> 6.875 | AA71: =M71*$AA$15 -> 0 | AB71: =M71*$AB$15 -> 27.5 | AC71: =M71*$AC$15 -> 27.5 | AD71: =M71*$AD$15 -> 27.5 | AE71: =M71*$AE$15 -> 110 | AF71: =L71*$AH$15 -> 0 | AG71: =M71*$AG$15 -> 0 | AH71: =M71*$AH$15 -> 0
B72: Vitrine 36 | C72: 550 | D72: 0 | E72: 0 | F72: 0 | G72: 0 | H72: 0 | I72: 0 | J72: 0 | K72: =(C72+D72+E72)*6% -> 33 | L72: 0 | M72: =C72+D72+E72+F72+G72+H72+J72+L72-I72 -> 550 | N72: =M72*$N$15 -> 132 | O72: =M72*$O$15 -> 43.541669 | P72: =M72*$P$15 -> 36.666669 | Q72: =M72*$Q$15 -> 43.541669 | R72: =M72*$R$15 -> 0 | S72: =M72*$S$15 -> 28.875 | T72: =M72*$T$15 -> 22 | U72: =M72*$U$15 -> 11 | V72: =M72*$U$15 -> 11 | W72: =M72*$W$15 -> 22 | X72: =M72*$X$15 -> 0 | Y72: =N72*$X$15 -> 0 | Z72: =M72*$Z$15 -> 6.875 | AA72: =M72*$AA$15 -> 0 | AB72: =M72*$AB$15 -> 27.5 | AC72: =M72*$AC$15 -> 27.5 | AD72: =M72*$AD$15 -> 27.5 | AE72: =M72*$AE$15 -> 110 | AF72: =L72*$AH$15 -> 0 | AG72: =M72*$AG$15 -> 0 | AH72: =M72*$AH$15 -> 0
B73: Vitrine 37 | C73: 514.7 | D73: 0 | E73: 0 | F73: 0 | G73: 0 | H73: 0 | I73: 0 | J73: 0 | K73: =(C73+D73+E73)*6% -> 30.882 | L73: 0 | M73: =C73+D73+E73+F73+G73+H73+J73+L73-I73 -> 514.7 | N73: =M73*$N$15 -> 123.528 | O73: =M73*$O$15 -> 40.747085 | P73: =M73*$P$15 -> 34.313335 | Q73: =M73*$Q$15 -> 40.747085 | R73: =M73*$R$15 -> 0 | S73: =M73*$S$15 -> 27.02175 | T73: =M73*$T$15 -> 20.588 | U73: =M73*$U$15 -> 10.294 | V73: =M73*$U$15 -> 10.294 | W73: =M73*$W$15 -> 20.588 | X73: =M73*$X$15 -> 0 | Y73: =N73*$X$15 -> 0 | Z73: =M73*$Z$15 -> 6.43375 | AA73: =M73*$AA$15 -> 0 | AB73: =M73*$AB$15 -> 25.735 | AC73: =M73*$AC$15 -> 25.735 | AD73: =M73*$AD$15 -> 25.735 | AE73: =M73*$AE$15 -> 102.94 | AF73: =L73*$AH$15 -> 0 | AG73: =M73*$AG$15 -> 0 | AH73: =M73*$AH$15 -> 0
B74: Vitrine 38 | C74: 500 | D74: 0 | E74: 0 | F74: 0 | G74: 0 | H74: 0 | I74: 0 | J74: 0 | K74: =(C74+D74+E74)*6% -> 30 | L74: 0 | M74: =C74+D74+E74+F74+G74+H74+J74+L74-I74 -> 500 | N74: =M74*$N$15 -> 120 | O74: =M74*$O$15 -> 39.583335 | P74: =M74*$P$15 -> 33.333335 | Q74: =M74*$Q$15 -> 39.583335 | R74: =M74*$R$15 -> 0 | S74: =M74*$S$15 -> 26.25 | T74: =M74*$T$15 -> 20 | U74: =M74*$U$15 -> 10 | V74: =M74*$U$15 -> 10 | W74: =M74*$W$15 -> 20 | X74: =M74*$X$15 -> 0 | Y74: =N74*$X$15 -> 0 | Z74: =M74*$Z$15 -> 6.25 | AA74: =M74*$AA$15 -> 0 | AB74: =M74*$AB$15 -> 25 | AC74: =M74*$AC$15 -> 25 | AD74: =M74*$AD$15 -> 25 | AE74: =M74*$AE$15 -> 100 | AF74: =L74*$AH$15 -> 0 | AG74: =M74*$AG$15 -> 0 | AH74: =M74*$AH$15 -> 0
B75: Vitrine 39 | C75: 358.29 | D75: 0 | E75: 0 | F75: 0 | G75: 0 | H75: 0 | I75: 0 | J75: 0 | K75: =(C75+D75+E75)*6% -> 21.4974 | L75: 0 | M75: =C75+D75+E75+F75+G75+H75+J75+L75-I75 -> 358.29 | N75: =M75*$N$15 -> 85.9896 | O75: =M75*$O$15 -> 28.364626 | P75: =M75*$P$15 -> 23.886001 | Q75: =M75*$Q$15 -> 28.364626 | R75: =M75*$R$15 -> 0 | S75: =M75*$S$15 -> 18.810225 | T75: =M75*$T$15 -> 14.3316 | U75: =M75*$U$15 -> 7.1658 | V75: =M75*$U$15 -> 7.1658 | W75: =M75*$W$15 -> 14.3316 | X75: =M75*$X$15 -> 0 | Y75: =N75*$X$15 -> 0 | Z75: =M75*$Z$15 -> 4.478625 | AA75: =M75*$AA$15 -> 0 | AB75: =M75*$AB$15 -> 17.9145 | AC75: =M75*$AC$15 -> 17.9145 | AD75: =M75*$AD$15 -> 17.9145 | AE75: =M75*$AE$15 -> 71.658 | AF75: =L75*$AH$15 -> 0 | AG75: =M75*$AG$15 -> 0 | AH75: =M75*$AH$15 -> 0
B76: Vitrine 40 | C76: =277.71 -> 277.71 | D76: 0 | E76: 0 | F76: 0 | G76: 0 | H76: 0 | I76: 0 | J76: 0 | K76: =(C76+D76+E76)*6% -> 16.6626 | L76: 0 | M76: =C76+D76+E76+F76+G76+H76+J76+L76-I76 -> 277.71 | N76: =M76*$N$15 -> 66.6504 | O76: =M76*$O$15 -> 21.985376 | P76: =M76*$P$15 -> 18.514001 | Q76: =M76*$Q$15 -> 21.985376 | R76: =M76*$R$15 -> 0 | S76: =M76*$S$15 -> 14.579775 | T76: =M76*$T$15 -> 11.1084 | U76: =M76*$U$15 -> 5.5542 | V76: =M76*$U$15 -> 5.5542 | W76: =M76*$W$15 -> 11.1084 | X76: =M76*$X$15 -> 0 | Y76: =N76*$X$15 -> 0 | Z76: =M76*$Z$15 -> 3.471375 | AA76: =M76*$AA$15 -> 0 | AB76: =M76*$AB$15 -> 13.8855 | AC76: =M76*$AC$15 -> 13.8855 | AD76: =M76*$AD$15 -> 13.8855 | AE76: =M76*$AE$15 -> 55.542 | AF76: =L76*$AH$15 -> 0 | AG76: =M76*$AG$15 -> 0 | AH76: =M76*$AH$15 -> 0
B77: Vitrine 41 | C77: 500 | D77: 0 | E77: 0 | F77: 0 | G77: 0 | H77: 0 | I77: 0 | J77: 0 | K77: =(C77+D77+E77)*6% -> 30 | L77: 0 | M77: =C77+D77+E77+F77+G77+H77+J77+L77-I77 -> 500 | N77: =M77*$N$15 -> 120 | O77: =M77*$O$15 -> 39.583335 | P77: =M77*$P$15 -> 33.333335 | Q77: =M77*$Q$15 -> 39.583335 | R77: =M77*$R$15 -> 0 | S77: =M77*$S$15 -> 26.25 | T77: =M77*$T$15 -> 20 | U77: =M77*$U$15 -> 10 | V77: =M77*$U$15 -> 10 | W77: =M77*$W$15 -> 20 | X77: =M77*$X$15 -> 0 | Y77: =N77*$X$15 -> 0 | Z77: =M77*$Z$15 -> 6.25 | AA77: =M77*$AA$15 -> 0 | AB77: =M77*$AB$15 -> 25 | AC77: =M77*$AC$15 -> 25 | AD77: =M77*$AD$15 -> 25 | AE77: =M77*$AE$15 -> 100 | AF77: =L77*$AH$15 -> 0 | AG77: =M77*$AG$15 -> 0 | AH77: =M77*$AH$15 -> 0
B78: Vitrine 42 | C78: 360.42 | D78: 0 | E78: 0 | F78: 0 | G78: 0 | H78: 0 | I78: 0 | J78: 0 | K78: =(C78+D78+E78)*6% -> 21.6252 | L78: 0 | M78: =C78+D78+E78+F78+G78+H78+J78+L78-I78 -> 360.42 | N78: =M78*$N$15 -> 86.5008 | O78: =M78*$O$15 -> 28.533251 | P78: =M78*$P$15 -> 24.028001 | Q78: =M78*$Q$15 -> 28.533251 | R78: =M78*$R$15 -> 0 | S78: =M78*$S$15 -> 18.92205 | T78: =M78*$T$15 -> 14.4168 | U78: =M78*$U$15 -> 7.2084 | V78: =M78*$U$15 -> 7.2084 | W78: =M78*$W$15 -> 14.4168 | X78: =M78*$X$15 -> 0 | Y78: =N78*$X$15 -> 0 | Z78: =M78*$Z$15 -> 4.50525 | AA78: =M78*$AA$15 -> 0 | AB78: =M78*$AB$15 -> 18.021 | AC78: =M78*$AC$15 -> 18.021 | AD78: =M78*$AD$15 -> 18.021 | AE78: =M78*$AE$15 -> 72.084 | AF78: =L78*$AH$15 -> 0 | AG78: =M78*$AG$15 -> 0 | AH78: =M78*$AH$15 -> 0
B79: Vitrine 43 | C79: 600 | D79: 0 | E79: 0 | F79: 0 | G79: 0 | H79: 0 | I79: 0 | J79: 0 | K79: =(C79+D79+E79)*6% -> 36 | L79: 0 | M79: =C79+D79+E79+F79+G79+H79+J79+L79-I79 -> 600 | N79: =M79*$N$15 -> 144 | O79: =M79*$O$15 -> 47.500002 | P79: =M79*$P$15 -> 40.000002 | Q79: =M79*$Q$15 -> 47.500002 | R79: =M79*$R$15 -> 0 | S79: =M79*$S$15 -> 31.5 | T79: =M79*$T$15 -> 24 | U79: =M79*$U$15 -> 12 | V79: =M79*$U$15 -> 12 | W79: =M79*$W$15 -> 24 | X79: =M79*$X$15 -> 0 | Y79: =N79*$X$15 -> 0 | Z79: =M79*$Z$15 -> 7.5 | AA79: =M79*$AA$15 -> 0 | AB79: =M79*$AB$15 -> 30 | AC79: =M79*$AC$15 -> 30 | AD79: =M79*$AD$15 -> 30 | AE79: =M79*$AE$15 -> 120 | AF79: =L79*$AH$15 -> 0 | AG79: =M79*$AG$15 -> 0 | AH79: =M79*$AH$15 -> 0
B80: Vitrine 44 | C80: =301.45 -> 301.45 | D80: 0 | E80: 0 | F80: 0 | G80: 0 | H80: 0 | I80: 0 | J80: 0 | K80: =(C80+D80+E80)*6% -> 18.087 | L80: 0 | M80: =C80+D80+E80+F80+G80+H80+J80+L80-I80 -> 301.45 | N80: =M80*$N$15 -> 72.348 | O80: =M80*$O$15 -> 23.864793 | P80: =M80*$P$15 -> 20.096668 | Q80: =M80*$Q$15 -> 23.864793 | R80: =M80*$R$15 -> 0 | S80: =M80*$S$15 -> 15.826125 | T80: =M80*$T$15 -> 12.058 | U80: =M80*$U$15 -> 6.029 | V80: =M80*$U$15 -> 6.029 | W80: =M80*$W$15 -> 12.058 | X80: =M80*$X$15 -> 0 | Y80: =N80*$X$15 -> 0 | Z80: =M80*$Z$15 -> 3.768125 | AA80: =M80*$AA$15 -> 0 | AB80: =M80*$AB$15 -> 15.0725 | AC80: =M80*$AC$15 -> 15.0725 | AD80: =M80*$AD$15 -> 15.0725 | AE80: =M80*$AE$15 -> 60.29 | AF80: =L80*$AH$15 -> 0 | AG80: =M80*$AG$15 -> 0 | AH80: =M80*$AH$15 -> 0
B81: Vitrine 46 | C81: 345.92 | D81: 0 | E81: 0 | F81: 0 | G81: 0 | H81: 0 | I81: 0 | J81: 0 | K81: =(C81+D81+E81)*6% -> 20.7552 | L81: 0 | M81: =C81+D81+E81+F81+G81+H81+J81+L81-I81 -> 345.92 | N81: =M81*$N$15 -> 83.0208 | O81: =M81*$O$15 -> 27.385334 | P81: =M81*$P$15 -> 23.061334 | Q81: =M81*$Q$15 -> 27.385334 | R81: =M81*$R$15 -> 0 | S81: =M81*$S$15 -> 18.1608 | T81: =M81*$T$15 -> 13.8368 | U81: =M81*$U$15 -> 6.9184 | V81: =M81*$U$15 -> 6.9184 | W81: =M81*$W$15 -> 13.8368 | X81: =M81*$X$15 -> 0 | Y81: =N81*$X$15 -> 0 | Z81: =M81*$Z$15 -> 4.324 | AA81: =M81*$AA$15 -> 0 | AB81: =M81*$AB$15 -> 17.296 | AC81: =M81*$AC$15 -> 17.296 | AD81: =M81*$AD$15 -> 17.296 | AE81: =M81*$AE$15 -> 69.184 | AF81: =L81*$AH$15 -> 0 | AG81: =M81*$AG$15 -> 0 | AH81: =M81*$AH$15 -> 0
B82: Vitrine 48 | C82: 473.39 | D82: 0 | E82: 0 | F82: 0 | G82: 0 | H82: 0 | I82: 0 | J82: 0 | K82: =(C82+D82+E82)*6% -> 28.4034 | L82: 0 | M82: =C82+D82+E82+F82+G82+H82+J82+L82-I82 -> 473.39 | N82: =M82*$N$15 -> 113.6136 | O82: =M82*$O$15 -> 37.47671 | P82: =M82*$P$15 -> 31.559335 | Q82: =M82*$Q$15 -> 37.47671 | R82: =M82*$R$15 -> 0 | S82: =M82*$S$15 -> 24.852975 | T82: =M82*$T$15 -> 18.9356 | U82: =M82*$U$15 -> 9.4678 | V82: =M82*$U$15 -> 9.4678 | W82: =M82*$W$15 -> 18.9356 | X82: =M82*$X$15 -> 0 | Y82: =N82*$X$15 -> 0 | Z82: =M82*$Z$15 -> 5.917375 | AA82: =M82*$AA$15 -> 0 | AB82: =M82*$AB$15 -> 23.6695 | AC82: =M82*$AC$15 -> 23.6695 | AD82: =M82*$AD$15 -> 23.6695 | AE82: =M82*$AE$15 -> 94.678 | AF82: =L82*$AH$15 -> 0 | AG82: =M82*$AG$15 -> 0 | AH82: =M82*$AH$15 -> 0
B83: Vitrine 50 | C83: 400 | D83: 0 | E83: 0 | F83: 0 | G83: 0 | H83: 0 | I83: 0 | J83: 0 | K83: =(C83+D83+E83)*6% -> 24 | L83: 0 | M83: =C83+D83+E83+F83+G83+H83+J83+L83-I83 -> 400 | N83: =M83*$N$15 -> 96 | O83: =M83*$O$15 -> 31.666668 | P83: =M83*$P$15 -> 26.666668 | Q83: =M83*$Q$15 -> 31.666668 | R83: =M83*$R$15 -> 0 | S83: =M83*$S$15 -> 21 | T83: =M83*$T$15 -> 16 | U83: =M83*$U$15 -> 8 | V83: =M83*$U$15 -> 8 | W83: =M83*$W$15 -> 16 | X83: =M83*$X$15 -> 0 | Y83: =N83*$X$15 -> 0 | Z83: =M83*$Z$15 -> 5 | AA83: =M83*$AA$15 -> 0 | AB83: =M83*$AB$15 -> 20 | AC83: =M83*$AC$15 -> 20 | AD83: =M83*$AD$15 -> 20 | AE83: =M83*$AE$15 -> 80 | AF83: =L83*$AH$15 -> 0 | AG83: =M83*$AG$15 -> 0 | AH83: =M83*$AH$15 -> 0
B84: Vitrine 52 | C84: =651.91 -> 651.91 | D84: 0 | E84: 0 | F84: 0 | G84: 0 | H84: 0 | I84: 0 | J84: 0 | K84: =(C84+D84+E84)*6% -> 39.1146 | L84: 0 | M84: =C84+D84+E84+F84+G84+H84+J84+L84-I84 -> 651.91 | N84: =M84*$N$15 -> 156.4584 | O84: =M84*$O$15 -> 51.609544 | P84: =M84*$P$15 -> 43.460669 | Q84: =M84*$Q$15 -> 51.609544 | R84: =M84*$R$15 -> 0 | S84: =M84*$S$15 -> 34.225275 | T84: =M84*$T$15 -> 26.0764 | U84: =M84*$U$15 -> 13.0382 | V84: =M84*$U$15 -> 13.0382 | W84: =M84*$W$15 -> 26.0764 | X84: =M84*$X$15 -> 0 | Y84: =N84*$X$15 -> 0 | Z84: =M84*$Z$15 -> 8.148875 | AA84: =M84*$AA$15 -> 0 | AB84: =M84*$AB$15 -> 32.5955 | AC84: =M84*$AC$15 -> 32.5955 | AD84: =M84*$AD$15 -> 32.5955 | AE84: =M84*$AE$15 -> 130.382 | AF84: =L84*$AH$15 -> 0 | AG84: =M84*$AG$15 -> 0 | AH84: =M84*$AH$15 -> 0
B85: Vitrine 54 | C85: 325.99 | D85: 0 | E85: 0 | F85: 0 | G85: 0 | H85: 0 | I85: 0 | J85: 0 | K85: =(C85+D85+E85)*6% -> 19.5594 | L85: 0 | M85: =C85+D85+E85+F85+G85+H85+J85+L85-I85 -> 325.99 | N85: =M85*$N$15 -> 78.2376 | O85: =M85*$O$15 -> 25.807543 | P85: =M85*$P$15 -> 21.732668 | Q85: =M85*$Q$15 -> 25.807543 | R85: =M85*$R$15 -> 0 | S85: =M85*$S$15 -> 17.114475 | T85: =M85*$T$15 -> 13.0396 | U85: =M85*$U$15 -> 6.5198 | V85: =M85*$U$15 -> 6.5198 | W85: =M85*$W$15 -> 13.0396 | X85: =M85*$X$15 -> 0 | Y85: =N85*$X$15 -> 0 | Z85: =M85*$Z$15 -> 4.074875 | AA85: =M85*$AA$15 -> 0 | AB85: =M85*$AB$15 -> 16.2995 | AC85: =M85*$AC$15 -> 16.2995 | AD85: =M85*$AD$15 -> 16.2995 | AE85: =M85*$AE$15 -> 65.198 | AF85: =L85*$AH$15 -> 0 | AG85: =M85*$AG$15 -> 0 | AH85: =M85*$AH$15 -> 0
B86: Vitrine 56 | C86: 658.93 | D86: 0 | E86: 0 | F86: 0 | G86: 0 | H86: 0 | I86: 0 | J86: 0 | K86: =(C86+D86+E86)*6% -> 39.5358 | L86: 0 | M86: =C86+D86+E86+F86+G86+H86+J86+L86-I86 -> 658.93 | N86: =M86*$N$15 -> 158.1432 | O86: =M86*$O$15 -> 52.165294 | P86: =M86*$P$15 -> 43.928669 | Q86: =M86*$Q$15 -> 52.165294 | R86: =M86*$R$15 -> 0 | S86: =M86*$S$15 -> 34.593825 | T86: =M86*$T$15 -> 26.3572 | U86: =M86*$U$15 -> 13.1786 | V86: =M86*$U$15 -> 13.1786 | W86: =M86*$W$15 -> 26.3572 | X86: =M86*$X$15 -> 0 | Y86: =N86*$X$15 -> 0 | Z86: =M86*$Z$15 -> 8.236625 | AA86: =M86*$AA$15 -> 0 | AB86: =M86*$AB$15 -> 32.9465 | AC86: =M86*$AC$15 -> 32.9465 | AD86: =M86*$AD$15 -> 32.9465 | AE86: =M86*$AE$15 -> 131.786 | AF86: =L86*$AH$15 -> 0 | AG86: =M86*$AG$15 -> 0 | AH86: =M86*$AH$15 -> 0
B87: Vitrine 58 | C87: 452.19 | D87: 0 | E87: 0 | F87: 0 | G87: 0 | H87: 0 | I87: 0 | J87: 0 | K87: =(C87+D87+E87)*6% -> 27.1314 | L87: 0 | M87: =C87+D87+E87+F87+G87+H87+J87+L87-I87 -> 452.19 | N87: =M87*$N$15 -> 108.5256 | O87: =M87*$O$15 -> 35.798377 | P87: =M87*$P$15 -> 30.146002 | Q87: =M87*$Q$15 -> 35.798377 | R87: =M87*$R$15 -> 0 | S87: =M87*$S$15 -> 23.739975 | T87: =M87*$T$15 -> 18.0876 | U87: =M87*$U$15 -> 9.0438 | V87: =M87*$U$15 -> 9.0438 | W87: =M87*$W$15 -> 18.0876 | X87: =M87*$X$15 -> 0 | Y87: =N87*$X$15 -> 0 | Z87: =M87*$Z$15 -> 5.652375 | AA87: =M87*$AA$15 -> 0 | AB87: =M87*$AB$15 -> 22.6095 | AC87: =M87*$AC$15 -> 22.6095 | AD87: =M87*$AD$15 -> 22.6095 | AE87: =M87*$AE$15 -> 90.438 | AF87: =L87*$AH$15 -> 0 | AG87: =M87*$AG$15 -> 0 | AH87: =M87*$AH$15 -> 0
B88: Vitrine 60 | C88: 476.29 | D88: 0 | E88: 0 | F88: 0 | G88: 0 | H88: 0 | I88: 0 | J88: 0 | K88: =(C88+D88+E88)*6% -> 28.5774 | L88: 0 | M88: =C88+D88+E88+F88+G88+H88+J88+L88-I88 -> 476.29 | N88: =M88*$N$15 -> 114.3096 | O88: =M88*$O$15 -> 37.706293 | P88: =M88*$P$15 -> 31.752668 | Q88: =M88*$Q$15 -> 37.706293 | R88: =M88*$R$15 -> 0 | S88: =M88*$S$15 -> 25.005225 | T88: =M88*$T$15 -> 19.0516 | U88: =M88*$U$15 -> 9.5258 | V88: =M88*$U$15 -> 9.5258 | W88: =M88*$W$15 -> 19.0516 | X88: =M88*$X$15 -> 0 | Y88: =N88*$X$15 -> 0 | Z88: =M88*$Z$15 -> 5.953625 | AA88: =M88*$AA$15 -> 0 | AB88: =M88*$AB$15 -> 23.8145 | AC88: =M88*$AC$15 -> 23.8145 | AD88: =M88*$AD$15 -> 23.8145 | AE88: =M88*$AE$15 -> 95.258 | AF88: =L88*$AH$15 -> 0 | AG88: =M88*$AG$15 -> 0 | AH88: =M88*$AH$15 -> 0
B89: Vitrine 61 | C89: 550 | D89: 0 | E89: 0 | F89: 0 | G89: 0 | H89: 0 | I89: 0 | J89: 0 | K89: =(C89+D89+E89)*6% -> 33 | L89: 0 | M89: =C89+D89+E89+F89+G89+H89+J89+L89-I89 -> 550 | N89: =M89*$N$15 -> 132 | O89: =M89*$O$15 -> 43.541669 | P89: =M89*$P$15 -> 36.666669 | Q89: =M89*$Q$15 -> 43.541669 | R89: =M89*$R$15 -> 0 | S89: =M89*$S$15 -> 28.875 | T89: =M89*$T$15 -> 22 | U89: =M89*$U$15 -> 11 | V89: =M89*$U$15 -> 11 | W89: =M89*$W$15 -> 22 | X89: =M89*$X$15 -> 0 | Y89: =N89*$X$15 -> 0 | Z89: =M89*$Z$15 -> 6.875 | AA89: =M89*$AA$15 -> 0 | AB89: =M89*$AB$15 -> 27.5 | AC89: =M89*$AC$15 -> 27.5 | AD89: =M89*$AD$15 -> 27.5 | AE89: =M89*$AE$15 -> 110 | AF89: =L89*$AH$15 -> 0 | AG89: =M89*$AG$15 -> 0 | AH89: =M89*$AH$15 -> 0
B90: Vitrine 63 | C90: 0 | D90: 0 | E90: 0 | F90: 0 | G90: 0 | H90: 0 | I90: 0 | J90: 0 | K90: =(C90+D90+E90)*6% -> 0 | L90: 0 | M90: =C90+D90+E90+F90+G90+H90+J90+L90-I90 -> 0 | N90: =M90*$N$15 -> 0 | O90: =M90*$O$15 -> 0 | P90: =M90*$P$15 -> 0 | Q90: =M90*$Q$15 -> 0 | R90: =M90*$R$15 -> 0 | S90: =M90*$S$15 -> 0 | T90: =M90*$T$15 -> 0 | U90: =M90*$U$15 -> 0 | V90: =M90*$U$15 -> 0 | W90: =M90*$W$15 -> 0 | X90: =M90*$X$15 -> 0 | Y90: =N90*$X$15 -> 0 | Z90: =M90*$Z$15 -> 0 | AA90: =M90*$AA$15 -> 0 | AB90: =M90*$AB$15 -> 0 | AC90: =M90*$AC$15 -> 0 | AD90: =M90*$AD$15 -> 0 | AE90: =M90*$AE$15 -> 0 | AF90: =L90*$AH$15 -> 0 | AG90: =M90*$AG$15 -> 0 | AH90: =M90*$AH$15 -> 0
B91: Quiosque 1 | C91: 0 | D91: 0 | E91: 0 | F91: 0 | G91: 0 | H91: 0 | I91: 0 | J91: 0 | K91: =(C91+D91+E91)*6% -> 0 | L91: 0 | M91: =C91+D91+E91+F91+G91+H91+J91+L91-I91 -> 0 | N91: =M91*$N$15 -> 0 | O91: =M91*$O$15 -> 0 | P91: =M91*$P$15 -> 0 | Q91: =M91*$Q$15 -> 0 | R91: =M91*$R$15 -> 0 | S91: =M91*$S$15 -> 0 | T91: =M91*$T$15 -> 0 | U91: =M91*$U$15 -> 0 | V91: =M91*$U$15 -> 0 | W91: =M91*$W$15 -> 0 | X91: =M91*$X$15 -> 0 | Y91: =N91*$X$15 -> 0 | Z91: =M91*$Z$15 -> 0 | AA91: =M91*$AA$15 -> 0 | AB91: =M91*$AB$15 -> 0 | AC91: =M91*$AC$15 -> 0 | AD91: =M91*$AD$15 -> 0 | AE91: =M91*$AE$15 -> 0 | AF91: =L91*$AH$15 -> 0 | AG91: =M91*$AG$15 -> 0 | AH91: =M91*$AH$15 -> 0
B92: 1ºA | C92: 0 | D92: 0 | E92: 0 | F92: 0 | G92: 0 | H92: 0 | I92: 0 | J92: 0 | K92: =(C92+D92+E92)*6% -> 0 | L92: 0 | M92: =C92+D92+E92+F92+G92+H92+J92+L92-I92 -> 0 | N92: =M92*$N$15 -> 0 | O92: =M92*$O$15 -> 0 | P92: =M92*$P$15 -> 0 | Q92: =M92*$Q$15 -> 0 | R92: =M92*$R$15 -> 0 | S92: =M92*$S$15 -> 0 | T92: =M92*$T$15 -> 0 | U92: =M92*$U$15 -> 0 | V92: =M92*$U$15 -> 0 | W92: =M92*$W$15 -> 0 | X92: =M92*$X$15 -> 0 | Y92: =N92*$X$15 -> 0 | Z92: =M92*$Z$15 -> 0 | AA92: =M92*$AA$15 -> 0 | AB92: =M92*$AB$15 -> 0 | AC92: =M92*$AC$15 -> 0 | AD92: =M92*$AD$15 -> 0 | AE92: =M92*$AE$15 -> 0 | AF92: =L92*$AH$15 -> 0 | AG92: =M92*$AG$15 -> 0 | AH92: =M92*$AH$15 -> 0
B93: 1ºB | C93: 380.39 | D93: 0 | E93: 0 | F93: 368.17 | G93: 66.53 | H93: 0 | I93: 0 | J93: 0 | K93: =(C93+D93+E93)*6% -> 22.8234 | L93: 0 | M93: =C93+D93+E93+F93+G93+H93+J93+L93-I93 -> 815.09 | N93: =M93*$N$15 -> 195.6216 | O93: =M93*$O$15 -> 64.527961 | P93: =M93*$P$15 -> 54.339336 | Q93: =M93*$Q$15 -> 64.527961 | R93: =M93*$R$15 -> 0 | S93: =M93*$S$15 -> 42.792225 | T93: =M93*$T$15 -> 32.6036 | U93: =M93*$U$15 -> 16.3018 | V93: =M93*$U$15 -> 16.3018 | W93: =M93*$W$15 -> 32.6036 | X93: =M93*$X$15 -> 0 | Y93: =N93*$X$15 -> 0 | Z93: =M93*$Z$15 -> 10.188625 | AA93: =M93*$AA$15 -> 0 | AB93: =M93*$AB$15 -> 40.7545 | AC93: =M93*$AC$15 -> 40.7545 | AD93: =M93*$AD$15 -> 40.7545 | AE93: =M93*$AE$15 -> 163.018 | AF93: =L93*$AH$15 -> 0 | AG93: =M93*$AG$15 -> 0 | AH93: =M93*$AH$15 -> 0
B94: 1ºC | C94: 480.68 | D94: 0 | E94: 0 | F94: 359.67 | G94: 64.99 | H94: 0 | I94: 0 | J94: 0 | K94: =(C94+D94+E94)*6% -> 28.8408 | L94: 0 | M94: =C94+D94+E94+F94+G94+H94+J94+L94-I94 -> 905.34 | N94: =M94*$N$15 -> 217.2816 | O94: =M94*$O$15 -> 71.672753 | P94: =M94*$P$15 -> 60.356003 | Q94: =M94*$Q$15 -> 71.672753 | R94: =M94*$R$15 -> 0 | S94: =M94*$S$15 -> 47.53035 | T94: =M94*$T$15 -> 36.2136 | U94: =M94*$U$15 -> 18.1068 | V94: =M94*$U$15 -> 18.1068 | W94: =M94*$W$15 -> 36.2136 | X94: =M94*$X$15 -> 0 | Y94: =N94*$X$15 -> 0 | Z94: =M94*$Z$15 -> 11.31675 | AA94: =M94*$AA$15 -> 0 | AB94: =M94*$AB$15 -> 45.267 | AC94: =M94*$AC$15 -> 45.267 | AD94: =M94*$AD$15 -> 45.267 | AE94: =M94*$AE$15 -> 181.068 | AF94: =L94*$AH$15 -> 0 | AG94: =M94*$AG$15 -> 0 | AH94: =M94*$AH$15 -> 0
B95: 1ºD | C95: =451 -> 451 | D95: 0 | E95: 0 | F95: 370.44 | G95: 64.25 | H95: 0 | I95: 0 | J95: 0 | K95: =(C95+D95+E95)*6% -> 27.06 | L95: 0 | M95: =C95+D95+E95+F95+G95+H95+J95+L95-I95 -> 885.69 | N95: =M95*$N$15 -> 212.5656 | O95: =M95*$O$15 -> 70.117128 | P95: =M95*$P$15 -> 59.046003 | Q95: =M95*$Q$15 -> 70.117128 | R95: =M95*$R$15 -> 0 | S95: =M95*$S$15 -> 46.498725 | T95: =M95*$T$15 -> 35.4276 | U95: =M95*$U$15 -> 17.7138 | V95: =M95*$U$15 -> 17.7138 | W95: =M95*$W$15 -> 35.4276 | X95: =M95*$X$15 -> 0 | Y95: =N95*$X$15 -> 0 | Z95: =M95*$Z$15 -> 11.071125 | AA95: =M95*$AA$15 -> 0 | AB95: =M95*$AB$15 -> 44.2845 | AC95: =M95*$AC$15 -> 44.2845 | AD95: =M95*$AD$15 -> 44.2845 | AE95: =M95*$AE$15 -> 177.138 | AF95: =L95*$AH$15 -> 0 | AG95: =M95*$AG$15 -> 0 | AH95: =M95*$AH$15 -> 0
B96: 1ºE | C96: =541.02 -> 541.02 | D96: 0 | E96: 0 | F96: 437.06 | G96: 75.7 | H96: 0 | I96: 0 | J96: 0 | K96: =(C96+D96+E96)*6% -> 32.4612 | L96: 0 | M96: =C96+D96+E96+F96+G96+H96+J96+L96-I96 -> 1053.78 | N96: =M96*$N$15 -> 252.9072 | O96: =M96*$O$15 -> 83.424254 | P96: =M96*$P$15 -> 70.252004 | Q96: =M96*$Q$15 -> 83.424254 | R96: =M96*$R$15 -> 0 | S96: =M96*$S$15 -> 55.32345 | T96: =M96*$T$15 -> 42.1512 | U96: =M96*$U$15 -> 21.0756 | V96: =M96*$U$15 -> 21.0756 | W96: =M96*$W$15 -> 42.1512 | X96: =M96*$X$15 -> 0 | Y96: =N96*$X$15 -> 0 | Z96: =M96*$Z$15 -> 13.17225 | AA96: =M96*$AA$15 -> 0 | AB96: =M96*$AB$15 -> 52.689 | AC96: =M96*$AC$15 -> 52.689 | AD96: =M96*$AD$15 -> 52.689 | AE96: =M96*$AE$15 -> 210.756 | AF96: =L96*$AH$15 -> 0 | AG96: =M96*$AG$15 -> 0 | AH96: =M96*$AH$15 -> 0
B97: 1ºF | C97: =566.24-53.12 -> 513.12 | D97: 0 | E97: 0 | F97: 388.63 | G97: 73.2 | H97: 0 | I97: 0 | J97: 0 | K97: =(C97+D97+E97)*6% -> 30.7872 | L97: 0 | M97: =C97+D97+E97+F97+G97+H97+J97+L97-I97 -> 974.95 | N97: =M97*$N$15 -> 233.988 | O97: =M97*$O$15 -> 77.183545 | P97: =M97*$P$15 -> 64.99667 | Q97: =M97*$Q$15 -> 77.183545 | R97: =M97*$R$15 -> 0 | S97: =M97*$S$15 -> 51.184875 | T97: =M97*$T$15 -> 38.998 | U97: =M97*$U$15 -> 19.499 | V97: =M97*$U$15 -> 19.499 | W97: =M97*$W$15 -> 38.998 | X97: =M97*$X$15 -> 0 | Y97: =N97*$X$15 -> 0 | Z97: =M97*$Z$15 -> 12.186875 | AA97: =M97*$AA$15 -> 0 | AB97: =M97*$AB$15 -> 48.7475 | AC97: =M97*$AC$15 -> 48.7475 | AD97: =M97*$AD$15 -> 48.7475 | AE97: =M97*$AE$15 -> 194.99 | AF97: =L97*$AH$15 -> 0 | AG97: =M97*$AG$15 -> 0 | AH97: =M97*$AH$15 -> 0
B98: 1ºG | C98: 438.1 | D98: 0 | E98: 0 | F98: 197.28 | G98: 37.18 | H98: 0 | I98: 0 | J98: 0 | K98: =(C98+D98+E98)*6% -> 26.286 | L98: 0 | M98: =C98+D98+E98+F98+G98+H98+J98+L98-I98 -> 672.56 | N98: =M98*$N$15 -> 161.4144 | O98: =M98*$O$15 -> 53.244336 | P98: =M98*$P$15 -> 44.837336 | Q98: =M98*$Q$15 -> 53.244336 | R98: =M98*$R$15 -> 0 | S98: =M98*$S$15 -> 35.3094 | T98: =M98*$T$15 -> 26.9024 | U98: =M98*$U$15 -> 13.4512 | V98: =M98*$U$15 -> 13.4512 | W98: =M98*$W$15 -> 26.9024 | X98: =M98*$X$15 -> 0 | Y98: =N98*$X$15 -> 0 | Z98: =M98*$Z$15 -> 8.407 | AA98: =M98*$AA$15 -> 0 | AB98: =M98*$AB$15 -> 33.628 | AC98: =M98*$AC$15 -> 33.628 | AD98: =M98*$AD$15 -> 33.628 | AE98: =M98*$AE$15 -> 134.512 | AF98: =L98*$AH$15 -> 0 | AG98: =M98*$AG$15 -> 0 | AH98: =M98*$AH$15 -> 0
B99: 1ºH | C99: =351.45 -> 351.45 | D99: 0 | E99: 0 | F99: 208.84 | G99: 39.91 | H99: 0 | I99: 0 | J99: 0 | K99: =(C99+D99+E99)*6% -> 21.087 | L99: 0 | M99: =C99+D99+E99+F99+G99+H99+J99+L99-I99 -> 600.2 | N99: =M99*$N$15 -> 144.048 | O99: =M99*$O$15 -> 47.515835 | P99: =M99*$P$15 -> 40.013335 | Q99: =M99*$Q$15 -> 47.515835 | R99: =M99*$R$15 -> 0 | S99: =M99*$S$15 -> 31.5105 | T99: =M99*$T$15 -> 24.008 | U99: =M99*$U$15 -> 12.004 | V99: =M99*$U$15 -> 12.004 | W99: =M99*$W$15 -> 24.008 | X99: =M99*$X$15 -> 0 | Y99: =N99*$X$15 -> 0 | Z99: =M99*$Z$15 -> 7.5025 | AA99: =M99*$AA$15 -> 0 | AB99: =M99*$AB$15 -> 30.01 | AC99: =M99*$AC$15 -> 30.01 | AD99: =M99*$AD$15 -> 30.01 | AE99: =M99*$AE$15 -> 120.04 | AF99: =L99*$AH$15 -> 0 | AG99: =M99*$AG$15 -> 0 | AH99: =M99*$AH$15 -> 0
B100: 1ºI | C100: 486.23 | D100: 0 | E100: 0 | F100: 390.7 | G100: 74.77 | H100: 0 | I100: 0 | J100: 0 | K100: =(C100+D100+E100)*6% -> 29.1738 | L100: 0 | M100: =C100+D100+E100+F100+G100+H100+J100+L100-I100 -> 951.7 | N100: =M100*$N$15 -> 228.408 | O100: =M100*$O$15 -> 75.34292 | P100: =M100*$P$15 -> 63.44667 | Q100: =M100*$Q$15 -> 75.34292 | R100: =M100*$R$15 -> 0 | S100: =M100*$S$15 -> 49.96425 | T100: =M100*$T$15 -> 38.068 | U100: =M100*$U$15 -> 19.034 | V100: =M100*$U$15 -> 19.034 | W100: =M100*$W$15 -> 38.068 | X100: =M100*$X$15 -> 0 | Y100: =N100*$X$15 -> 0 | Z100: =M100*$Z$15 -> 11.89625 | AA100: =M100*$AA$15 -> 0 | AB100: =M100*$AB$15 -> 47.585 | AC100: =M100*$AC$15 -> 47.585 | AD100: =M100*$AD$15 -> 47.585 | AE100: =M100*$AE$15 -> 190.34 | AF100: =L100*$AH$15 -> 0 | AG100: =M100*$AG$15 -> 0 | AH100: =M100*$AH$15 -> 0
B101: 1ºJ | C101: 481.68 | D101: 58.34 | E101: 0 | F101: 260.04 | G101: 49.69 | H101: 0 | I101: 0 | J101: 0 | K101: =(C101+D101+E101)*6% -> 32.4012 | L101: 0 | M101: =C101+D101+E101+F101+G101+H101+J101+L101-I101 -> 849.75 | N101: =M101*$N$15 -> 203.94 | O101: =M101*$O$15 -> 67.271878 | P101: =M101*$P$15 -> 56.650003 | Q101: =M101*$Q$15 -> 67.271878 | R101: =M101*$R$15 -> 0 | S101: =M101*$S$15 -> 44.611875 | T101: =M101*$T$15 -> 33.99 | U101: =M101*$U$15 -> 16.995 | V101: =M101*$U$15 -> 16.995 | W101: =M101*$W$15 -> 33.99 | X101: =M101*$X$15 -> 0 | Y101: =N101*$X$15 -> 0 | Z101: =M101*$Z$15 -> 10.621875 | AA101: =M101*$AA$15 -> 0 | AB101: =M101*$AB$15 -> 42.4875 | AC101: =M101*$AC$15 -> 42.4875 | AD101: =M101*$AD$15 -> 42.4875 | AE101: =M101*$AE$15 -> 169.95 | AF101: =L101*$AH$15 -> 0 | AG101: =M101*$AG$15 -> 0 | AH101: =M101*$AH$15 -> 0
B102: 1ºK | C102: 0 | D102: 0 | E102: 630 | F102: 0 | G102: 0 | H102: 0 | I102: 0 | J102: 0 | K102: =(C102+D102+E102)*6% -> 37.8 | L102: 0 | M102: =C102+D102+E102+F102+G102+H102+J102+L102-I102 -> 630 | N102: =M102*$N$15 -> 151.2 | O102: =M102*$O$15 -> 49.875002 | P102: =M102*$P$15 -> 42.000002 | Q102: =M102*$Q$15 -> 49.875002 | R102: =M102*$R$15 -> 0 | S102: =M102*$S$15 -> 33.075 | T102: =M102*$T$15 -> 25.2 | U102: =M102*$U$15 -> 12.6 | V102: =M102*$U$15 -> 12.6 | W102: =M102*$W$15 -> 25.2 | X102: =M102*$X$15 -> 0 | Y102: =N102*$X$15 -> 0 | Z102: =M102*$Z$15 -> 7.875 | AA102: =M102*$AA$15 -> 0 | AB102: =M102*$AB$15 -> 31.5 | AC102: =M102*$AC$15 -> 31.5 | AD102: =M102*$AD$15 -> 31.5 | AE102: =M102*$AE$15 -> 126 | AF102: =L102*$AH$15 -> 0 | AG102: =M102*$AG$15 -> 0 | AH102: =M102*$AH$15 -> 0
B103: 1ºL | C103: 650 | D103: =65+6.5 -> 71.5 | E103: 0 | F103: 0 | G103: 0 | H103: 0 | I103: 0 | J103: 0 | K103: =(C103+D103+E103)*6% -> 43.29 | L103: 0 | M103: =C103+D103+E103+F103+G103+H103+J103+L103-I103 -> 721.5 | N103: =M103*$N$15 -> 173.16 | O103: =M103*$O$15 -> 57.118752 | P103: =M103*$P$15 -> 48.100002 | Q103: =M103*$Q$15 -> 57.118752 | R103: =M103*$R$15 -> 0 | S103: =M103*$S$15 -> 37.87875 | T103: =M103*$T$15 -> 28.86 | U103: =M103*$U$15 -> 14.43 | V103: =M103*$U$15 -> 14.43 | W103: =M103*$W$15 -> 28.86 | X103: =M103*$X$15 -> 0 | Y103: =N103*$X$15 -> 0 | Z103: =M103*$Z$15 -> 9.01875 | AA103: =M103*$AA$15 -> 0 | AB103: =M103*$AB$15 -> 36.075 | AC103: =M103*$AC$15 -> 36.075 | AD103: =M103*$AD$15 -> 36.075 | AE103: =M103*$AE$15 -> 144.3 | AF103: =L103*$AH$15 -> 0 | AG103: =M103*$AG$15 -> 0 | AH103: =M103*$AH$15 -> 0
B104: 1ºM | C104: 384.62 | D104: 0 | E104: 0 | F104: 706.88 | G104: 0 | H104: 0 | I104: 0 | J104: 0 | K104: =(C104+D104+E104)*6% -> 23.0772 | L104: 0 | M104: =C104+D104+E104+F104+G104+H104+J104+L104-I104 -> 1091.5 | N104: =M104*$N$15 -> 261.96 | O104: =M104*$O$15 -> 86.41042 | P104: =M104*$P$15 -> 72.76667 | Q104: =M104*$Q$15 -> 86.41042 | R104: =M104*$R$15 -> 0 | S104: =M104*$S$15 -> 57.30375 | T104: =M104*$T$15 -> 43.66 | U104: =M104*$U$15 -> 21.83 | V104: =M104*$U$15 -> 21.83 | W104: =M104*$W$15 -> 43.66 | X104: =M104*$X$15 -> 0 | Y104: =N104*$X$15 -> 0 | Z104: =M104*$Z$15 -> 13.64375 | AA104: =M104*$AA$15 -> 0 | AB104: =M104*$AB$15 -> 54.575 | AC104: =M104*$AC$15 -> 54.575 | AD104: =M104*$AD$15 -> 54.575 | AE104: =M104*$AE$15 -> 218.3 | AF104: =L104*$AH$15 -> 0 | AG104: =M104*$AG$15 -> 0 | AH104: =M104*$AH$15 -> 0
B105: 2ºA | C105: 557.91 | D105: 0 | E105: 0 | F105: 363.13 | G105: 65.6 | H105: 0 | I105: 0 | J105: 0 | K105: =(C105+D105+E105)*6% -> 33.4746 | L105: 0 | M105: =C105+D105+E105+F105+G105+H105+J105+L105-I105 -> 986.64 | N105: =M105*$N$15 -> 236.7936 | O105: =M105*$O$15 -> 78.109003 | P105: =M105*$P$15 -> 65.776003 | Q105: =M105*$Q$15 -> 78.109003 | R105: =M105*$R$15 -> 0 | S105: =M105*$S$15 -> 51.7986 | T105: =M105*$T$15 -> 39.4656 | U105: =M105*$U$15 -> 19.7328 | V105: =M105*$U$15 -> 19.7328 | W105: =M105*$W$15 -> 39.4656 | X105: =M105*$X$15 -> 0 | Y105: =N105*$X$15 -> 0 | Z105: =M105*$Z$15 -> 12.333 | AA105: =M105*$AA$15 -> 0 | AB105: =M105*$AB$15 -> 49.332 | AC105: =M105*$AC$15 -> 49.332 | AD105: =M105*$AD$15 -> 49.332 | AE105: =M105*$AE$15 -> 197.328 | AF105: =L105*$AH$15 -> 0 | AG105: =M105*$AG$15 -> 0 | AH105: =M105*$AH$15 -> 0
...

Sheet Dist. Despesas
B5: DISTRIBUIÇÃO DE DESPESAS - MAIO/2026
B7: DESPESAS | C7: VALOR | D7: ROPSIME C | E7: CAROLINE | F7: THYAGO | G7: FREDERICO | H7: EDDA | I7: CLAUDINA | J7: VARAM | K7: M. TERESA | L7: HENRIQUE G. | M7: ADRIANA | N7: CAROLINA | O7: FKZ | P7: M. ANTONIO | Q7: JULIANA | R7: MONIQUE | S7: VIVIANNE | T7: DENISE | U7: ROPSIMÉ | V7: KEUTE | W7: HALLELUJAH | X7: ROKE
D8: 0.24 | E8: 0.07916667 | F8: 0.06666667 | G8: 0.07916667 | H8: 0 | I8: 0.0525 | J8: 0.04 | K8: 0.02 | L8: 0.02 | M8: 0.04 | N8: 0 | O8: 0 | P8: 0.0125 | Q8: 0 | R8: 0.05 | S8: 0.05 | T8: 0.05 | U8: 0.2 | V8: 0 | W8: 0 | X8: 0
B9: Honorários Administrativos - Ed. Claudina | C9: =SUM(Receitas!K12:K296) -> 7751.1354 | D9: =C9*$D$8 -> 1860.2725 | E9: =$C$9*E8 -> 613.63158 | F9: =$C$9*F8 -> 516.74239 | G9: =$C$9*G8 -> 613.63158 | H9: =$C$9*H8 -> 0 | I9: =$C$9*I8 -> 406.93461 | J9: =$C$9*J8 -> 310.04542 | K9: =$C$9*K8 -> 155.02271 | L9: =$C$9*L8 -> 155.02271 | ... X9: =$C$9*X8 -> 0
B10: Retenção Fundo de Reserva Ed. Claudina - (3%) | C10: =C11*3% -> 5406.4209 | D10: =C10*$D$8 -> 1297.541 | E10: =$C$10*E8 -> 428.00834 | F10: =$C$10*F8 -> 360.42808 | G10: =$C$10*G8 -> 428.00834 | H10: =$C$10*H8 -> 0 | I10: =$C$10*I8 -> 283.8371 | J10: =$C$10*J8 -> 216.25684 | K10: =$C$10*K8 -> 108.12842 | L10: =$C$10*L8 -> 108.12842 | ... X10: =$C$10*X8 -> 0
B11: Condomínios - Ed. Claudina + IPTU | C11: =19440.6+160773.43 -> 180214.03 | D11: =C11*$D$8 -> 43251.367 | E11: =$C$11*E8 -> 14266.945 | F11: =$C$11*F8 -> 12014.269 | G11: =$C$11*G8 -> 14266.945 | H11: =$C$11*H8 -> 0 | I11: =$C$11*I8 -> 9461.2366 | J11: =$C$11*J8 -> 7208.5612 | K11: =$C$11*K8 -> 3604.2806 | L11: =$C$11*L8 -> 3604.2806 | ... X11: =$C$11*X8 -> 0
B12: Despesas com Cartório - Marcos K. e Outros | C12: 0 | D12: =C12*$D$8 -> 0 | E12: =$C$12*E8 -> 0 | F12: =$C$12*F8 -> 0 | G12: =$C$12*G8 -> 0 | H12: =$C$12*H8 -> 0 | I12: =$C$12*I8 -> 0 | J12: =$C$12*J8 -> 0 | K12: =$C$12*K8 -> 0 | L12: =$C$12*L8 -> 0 | ... X12: =$C$12*X8 -> 0
B13: Guias Judiciais - Processo CE Claudina | C13: 0 | D13: =C13*$D$8 -> 0 | E13: =$C$13*E8 -> 0 | F13: =$C$13*F8 -> 0 | G13: =$C$13*G8 -> 0 | H13: =$C$13*H8 -> 0 | I13: =$C$13*I8 -> 0 | J13: =$C$13*J8 -> 0 | K13: =$C$13*K8 -> 0 | L13: =$C$13*L8 -> 0 | ... X13: =$C$13*X8 -> 0
B14: SUB TOTAL: | C14: =SUM(C9:C13) -> 193371.59 | D14: =SUM(D9:D13) -> 46409.181 | E14: =SUM(E9:E13) -> 15308.585 | F14: =SUM(F9:F13) -> 12891.44 | G14: =SUM(G9:G13) -> 15308.585 | H14: =SUM(H9:H13) -> 0 | I14: =SUM(I9:I13) -> 10152.008 | J14: =SUM(J9:J13) -> 7734.8635 | ... X14: =SUM(X9:X13) -> 0
B15: DESPESAS | C15: VALOR | D15: ROPSIME C | E15: CAROLINE | F15: THYAGO | G15: FREDERICO | H15: EDDA | I15: CLAUDINA | J15: VARAM | K15: M. TERESA | L15: HENRIQUE G. | M15: ADRIANA | N15: CAROLINA | O15: FKZ | P15: M. ANTONIO | Q15: JULIANA | R15: MONIQUE | S15: VIVIANNE | T15: DENISE | U15: ROPSIMÉ | V15: KEUTE | W15: HALLELUJAH | X15: ROKE
D16: 0.24 | E16: 0 | F16: 0 | G16: 0 | H16: 0 | I16: 0.04 | J16: 0.04 | K16: 0.02 | L16: 0.02 | M16: 0 | N16: 0 | O16: 0.04 | P16: 0 | Q16: 0.05 | R16: 0.05 | S16: 0.05 | T16: 0.05 | U16: 0 | V16: 0.1 | W16: 0.1 | X16: 0.2
B17: Honorários administrativos - Outros Imóveis | C17: =SUM(Receitas!K8:K11) -> 15288.74 | D17: =$C$17*D16 -> 3669.2976 | E17: 0 | F17: =$C$17*F16 -> 0 | G17: 0 | H17: =$C$17*H16 -> 0 | I17: =$C$17*I16 -> 611.54959 | J17: =$C$17*J16 -> 611.54959 | K17: =$C$17*K16 -> 305.7748 | L17: =$C$17*L16 -> 305.7748 | M17: =$C$17*M16 -> 0 | N17: =$C$17*N16 -> 0 | O17: =$C$17*O16 -> 611.54959 | ... T17: =$C$17*T16 -> 764.43699 | U17: 0 | V17: =$C$17*V16 -> 1528.874 | W17: =$C$17*W16 -> 1528.874 | X17: =C17*X16 -> 3057.748
B18: SUB TOTAL: | C18: =SUM(C17:C17) -> 15288.74 | D18: =SUM(D17:D17) -> 3669.2976 | E18: =SUM(E17:E17) -> 0 | F18: =SUM(F17:F17) -> 0 | G18: =SUM(G17:G17) -> 0 | H18: =SUM(H17:H17) -> 0 | I18: =SUM(I17:I17) -> 611.54959 | J18: =SUM(J17:J17) -> 611.54959 | ... X18: =SUM(X17:X17) -> 3057.748
B19: DESPESAS | C19: VALOR | D19: ROPSIME C | E19: CAROLINE | F19: THYAGO | G19: FREDERICO | H19: EDDA | I19: CLAUDINA | J19: VARAM | K19: M. TERESA | L19: HENRIQUE G. | M19: ADRIANA | N19: CAROLINA | O19: FKZ | P19: M. ANTONIO | Q19: JULIANA | R19: MONIQUE | S19: VIVIANNE | T19: DENISE | U19: ROPSIMÉ | V19: KEUTE | W19: HALLELUJAH | X19: ROKE
D20: 0.24 | E20: 0 | F20: 0 | G20: 0 | H20: 0 | I20: 0.04 | J20: 0.04 | K20: 0.02 | L20: 0.02 | M20: 0 | N20: 0 | O20: 0.04 | P20: 0 | Q20: 0.05 | R20: 0.05 | S20: 0.05 | T20: 0.05 | U20: 0 | V20: 0.1 | W20: 0.1 | X20: 0.2
B21: IPTU - Parcela 03/10 - Florêncio de Abreu 60,66,70 e 74 | C21: 23604.48 | D21: =C21*$D$20 -> 5665.0752 | E21: 0 | F21: =$C$21*F20 -> 0 | G21: =$C$21*G20 -> 0 | H21: =$C$21*H20 -> 0 | I21: =$C$21*I20 -> 944.1792 | J21: =$C$21*J20 -> 944.1792 | K21: =$C$21*K20 -> 472.0896 | L21: =$C$21*L20 -> 472.0896 | M21: =$C$21*M20 -> 0 | ... X21: =$C$21*X20 -> 4720.896
B22: IPTU - Parcela 04/10 - R. 25 de Março, 661,669 | C22: 31813.47 | D22: =C22*$D$20 -> 7635.2328 | E22: =$C$22*E20 -> 0 | F22: =$C$22*F20 -> 0 | G22: =$C$22*G20 -> 0 | H22: =$C$22*H20 -> 0 | I22: =$C$22*I20 -> 1272.5388 | J22: =$C$22*J20 -> 1272.5388 | K22: =$C$22*K20 -> 636.2694 | L22: =$C$22*L20 -> 636.2694 | ... X22: =$C$22*X20 -> 6362.694
B23: Regularização - 25 de Março | C23: 0 | D23: =C23*$D$20 -> 0 | E23: =$C$23*E20 -> 0 | F23: =$C$23*F20 -> 0 | G23: =$C$23*G20 -> 0 | H23: =$C$23*H20 -> 0 | I23: =$C$23*I20 -> 0 | J23: =$C$23*J20 -> 0 | K23: =$C$23*K20 -> 0 | L23: =$C$23*L20 -> 0 | ... X23: =$C$23*X20 -> 0
B24: ThyssenKrupp - 25 de Março | C24: =1451.81+1051.25+4637.69 -> 7140.75 | D24: =C24*$D$20 -> 1713.78 | E24: =$C$24*E20 -> 0 | F24: =$C$24*F20 -> 0 | G24: =$C$24*G20 -> 0 | H24: =$C$24*H20 -> 0 | I24: =$C$24*I20 -> 285.63 | J24: =$C$24*J20 -> 285.63 | K24: =$C$24*K20 -> 142.815 | L24: =$C$24*L20 -> 142.815 | ... X24: =$C$24*X20 -> 1428.15
B25: SUB TOTAL: | C25: =SUM(C21:C24) -> 62558.7 | D25: =SUM(D21:D24) -> 15014.088 | E25: =SUM(E21:E24) -> 0 | F25: =SUM(F21:F24) -> 0 | G25: =SUM(G21:G24) -> 0 | H25: =SUM(H21:H24) -> 0 | I25: =SUM(I21:I24) -> 2502.348 | J25: =SUM(J21:J24) -> 2502.348 | ... X25: =SUM(X21:X24) -> 12511.74
B26: DESPESAS | C26: VALOR | D26: ROPSIME C | E26: CAROLINE | F26: THYAGO | G26: FREDERICO | H26: EDDA | I26: CLAUDINA | J26: VARAM | K26: M. TERESA | L26: HENRIQUE G. | M26: ADRIANA | N26: CAROLINA | O26: FKZ | P26: M. ANTONIO | Q26: JULIANA | R26: MONIQUE | S26: VIVIANNE | T26: DENISE | U26: ROPSIMÉ | V26: KEUTE | W26: HALLELUJAH | X26: ROKE
D27: 0.3333333 | E27: 0.11111111 | F27: 0.11111111 | G27: 0.11111111 | H27: 0.25 | I27: 0.01666667 | J27: 0.01666667 | K27: 0.00833333 | L27: =K27 -> 0.00833333 | M27: 0.01666667 | N27: 0.01666667 | O27: 0 | P27: 0 | Q27: 0 | R27: 0 | S27: 0 | T27: 0 | U27: 0 | V27: 0 | W27: 0 | X27: 0
B28: IPTU - Parcela 03/10 - R. Maria Amália L Azevedo, S/N | C28: 2261.93 | D28: =C28*$D$27 -> 753.97659 | E28: =$C$28*E27 -> 251.32555 | F28: =$C$28*F27 -> 251.32555 | G28: =$C$28*G27 -> 251.32555 | H28: =$C$28*H27 -> 565.4825 | I28: =$C$28*I27 -> 37.698841 | J28: =$C$28*J27 -> 37.698841 | K28: =$C$28*K27 -> 18.849409 | L28: =$C$28*L27 -> 18.849409 | ... X28: =$C$28*X27 -> 0
B29: Despesas - Limpeza do Terreno | C29: 2000 | D29: =$C$29*D27 -> 666.6666 | E29: =$C$29*E27 -> 222.22222 | F29: =$C$29*F27 -> 222.22222 | G29: =$C$29*G27 -> 222.22222 | H29: =$C$29*H27 -> 500 | I29: =$C$29*I27 -> 33.33334 | J29: =$C$29*J27 -> 33.33334 | K29: =$C$29*K27 -> 16.66666 | ... X29: =$C$29*X27 -> 0
B30: SUB TOTAL: | C30: =SUM(C28:C29) -> 4261.93 | D30: =SUM(D28:D29) -> 1420.6432 | E30: =SUM(E28:E29) -> 473.54777 | F30: =SUM(F28:F29) -> 473.54777 | G30: =SUM(G28:G29) -> 473.54777 | H30: =SUM(H28:H29) -> 1065.4825 | I30: =SUM(I28:I29) -> 71.032181 | J30: =SUM(J28:J29) -> 71.032181 | ... X30: =SUM(X28:X29) -> 0
B31: DESPESAS INDIVIDUAIS | C31: VALOR | D31: ROPSIME C | E31: CAROLINE | F31: THYAGO | G31: FREDERICO | H31: EDDA | I31: CLAUDINA | J31: VARAM | K31: M. TERESA | L31: HENRIQUE G. | M31: ADRIANA | N31: CAROLINA | O31: FKZ | P31: M. ANTONIO | Q31: JULIANA | R31: MONIQUE | S31: VIVIANNE | T31: DENISE | U31: ROPSIMÉ | V31: KEUTE | W31: HALLELUJAH | X31: ROKE
B33: Despesas Extraordináris - 5 Irmãos | C33: =1059.56 -> 1059.56 | D33: =C33*24% -> 254.2944 | E33: =$C$33*6.66667% -> 70.637369 | F33: =$C$33*6.66667% -> 70.637369 | G33: =$C$33*6.66667% -> 70.637369 | H33: 0 | I33: =$C$33*4% -> 42.3824 | J33: =$C$33*4% -> 42.3824 | K33: =$C$33*2% -> 21.1912 | L33: =$C$33*2% -> 21.1912 | M33: =$C$33*4% -> 42.3824 | N33: 0 | O33: 0 | P33: 0 | Q33: =$C$33*5% -> 52.978 | R33: =$C$33*5% -> 52.978 | S33: =$C$33*5% -> 52.978 | T33: =$C$33*5% -> 52.978 | U33: =C33*20% -> 211.912 | V33: 0 | W33: 0 | X33: 0
B34: Honorários Advocatícios(Astúrias Guarujá) | C34: =10000+1612.68+(46.57*11) -> 12124.95 | D34: 0 | E34: =$C$34/4/3 -> 1010.4125 | F34: =$C$34/4/3 -> 1010.4125 | G34: =$C$34/4/3 -> 1010.4125 | H34: =(C34/4)*0.75 -> 2273.4281 | I34: =$C$34/4*0.05 -> 151.56188 | J34: =$C$34/4*0.05 -> 151.56188 | K34: =$C$34/4*0.05/2 -> 75.780938 | L34: =$C$34/4*0.05/2 -> 75.780938 | M34: =$C$34/4*0.05 -> 151.56188 | N34: =$C$34/4*0.05 -> 151.56188 | O34: 0 | P34: 0 | Q34: =$C$34/4/4 -> 757.80938 | R34: =$C$34/4/4 -> 757.80938 | S34: =$C$34/4/4 -> 757.80938 | T34: =$C$34/4/4 -> 757.80938 | U34: =C34/4 -> 3031.2375 | V34: 0 | W34: 0 | X34: 0
B35: Despesas - Pericia Iguape | C35: 50000 | D35: 0 | E35: =C35/4/3 -> 4166.6667 | F35: =E35 -> 4166.6667 | G35: =F35 -> 4166.6667 | H35: =C35/4/2 -> 6250 | I35: =(C35/4/2)/5 -> 1250 | J35: =I35 -> 1250 | K35: =J35/2 -> 625 | L35: =K35 -> 625 | M35: =J35 -> 1250 | N35: =M35 -> 1250 | O35: 0 | P35: 0 | Q35: =C35/4/4 -> 3125 | R35: =Q35 -> 3125 | S35: =R35 -> 3125 | T35: =S35 -> 3125 | U35: =C35/4 -> 12500 | V35: 0 | W35: 0 | X35: 0
B36: Despesas - M. Teresa Gasparian | C36: 0 | D36: 0 | E36: 0 | F36: 0 | G36: 0 | H36: 0 | I36: 0 | J36: 0 | K36: =C36/2 -> 0 | L36: =K36 -> 0 | M36: 0 | N36: 0 | O36: 0 | P36: 0 | Q36: 0 | R36: 0 | S36: 0 | T36: 0 | U36: 0 | V36: 0 | W36: 0 | X36: 0
B37: Despesas - Vivianne H. | C37: 0 | D37: 0 | E37: 0 | F37: 0 | G37: 0 | H37: 0 | I37: 0 | J37: 0 | K37: 0 | L37: 0 | M37: 0 | N37: 0 | O37: 0 | P37: 0 | Q37: 0 | R37: 0 | S37: =C37 -> 0 | T37: 0 | U37: 0 | V37: 0 | W37: 0 | X37: 0
B38: Despesas - Ropsime Claudina V Keutenedjian | C38: 10092.3 | D38: =C38 -> 10092.3 | E38: 0 | F38: 0 | G38: 0 | H38: 0 | I38: 0 | J38: 0 | K38: 0 | L38: 0 | M38: 0 | N38: 0 | O38: 0 | P38: 0 | Q38: 0 | R38: 0 | S38: 0 | T38: 0 | U38: 0 | V38: 0 | W38: 0 | X38: 0
B39: Repasse (Mônica Lewandowski) | C39: =1161.3+8320.82 -> 9482.12 | D39: 0 | E39: 0 | F39: 0 | G39: 0 | H39: 0 | I39: 0 | J39: 0 | K39: 0 | L39: 0 | M39: 0 | N39: 0 | O39: 0 | P39: 0 | Q39: 0 | R39: =C39 -> 9482.12 | S39: 0 | T39: 0 | U39: 0 | V39: 0 | W39: 0 | X39: 0
B40: Repasse (Denise Haddad) | C40: =1161.3+8322.39 -> 9483.69 | D40: 0 | E40: 0 | F40: 0 | G40: 0 | H40: 0 | I40: 0 | J40: 0 | K40: 0 | L40: 0 | M40: 0 | N40: 0 | O40: 0 | P40: 0 | Q40: 0 | R40: 0 | S40: 0 | T40: =C40 -> 9483.69 | U40: 0 | V40: 0 | W40: 0 | X40: 0
B41: Repasse (Viviane Haddad) | C41: =8320.82+1161.3 -> 9482.12 | D41: 0 | E41: 0 | F41: 0 | G41: 0 | H41: 0 | I41: 0 | J41: 0 | K41: 0 | L41: 0 | M41: 0 | N41: 0 | O41: 0 | P41: 0 | Q41: 0 | R41: 0 | S41: =C41 -> 9482.12 | T41: 0 | U41: 0 | V41: 0 | W41: 0 | X41: 0
B42: Repasse (Juliana Mattos Haddad) | C42: 11096.52 | D42: 0 | E42: 0 | F42: 0 | G42: 0 | H42: 0 | I42: 0 | J42: 0 | K42: 0 | L42: 0 | M42: 0 | N42: 0 | O42: 0 | P42: 0 | Q42: =C42 -> 11096.52 | R42: 0 | S42: 0 | T42: 0 | U42: 0 | V42: 0 | W42: 0 | X42: 0
B43: Repasse (Marco Antônio Keutenedjian Milani) | C43: =290.33 -> 290.33 | D43: 0 | E43: 0 | F43: 0 | G43: 0 | H43: 0 | I43: 0 | J43: 0 | K43: 0 | L43: 0 | M43: 0 | N43: 0 | O43: 0 | P43: =C43 -> 290.33 | Q43: 0 | R43: 0 | S43: 0 | T43: 0 | U43: 0 | V43: 0 | W43: 0 | X43: 0
B44: Repasse(Claudina Keutenedjian) | C44: =1219.37+8758.75 -> 9978.12 | D44: 0 | E44: 0 | F44: 0 | G44: 0 | H44: 0 | I44: =C44 -> 9978.12 | J44: 0 | K44: 0 | L44: 0 | M44: 0 | N44: 0 | O44: 0 | P44: 0 | Q44: 0 | R44: 0 | S44: 0 | T44: 0 | U44: 0 | V44: 0 | W44: 0 | X44: 0
B45: Repasse (Adriana Keutenedjian) | C45: =929.04 -> 929.04 | D45: 0 | E45: 0 | F45: 0 | G45: 0 | H45: 0 | I45: 0 | J45: 0 | K45: 0 | L45: 0 | M45: =C45 -> 929.04 | N45: 0 | O45: 0 | P45: 0 | Q45: 0 | R45: 0 | S45: 0 | T45: 0 | U45: 0 | V45: 0 | W45: 0 | X45: 0
B46: Repasse (Varam Keutenedjian Neto) | C46: =929.04+8758.75 -> 9687.79 | D46: 0 | E46: 0 | F46: 0 | G46: 0 | H46: 0 | I46: 0 | J46: =C46 -> 9687.79 | K46: 0 | L46: 0 | M46: 0 | N46: 0 | O46: 0 | P46: 0 | Q46: 0 | R46: 0 | S46: 0 | T46: 0 | U46: 0 | V46: 0 | W46: 0 | X46: 0
B47: Repasse(Henrique Gasparian Keutenedjian) | C47: =464.52+4590.59 -> 5055.11 | D47: 0 | E47: 0 | F47: 0 | G47: 0 | H47: 0 | I47: 0 | J47: 0 | K47: 0 | L47: =C47 -> 5055.11 | M47: 0 | N47: 0 | O47: 0 | P47: 0 | Q47: 0 | R47: 0 | S47: 0 | T47: 0 | U47: 0 | V47: 0 | W47: 0 | X47: 0
B48: Repasse(M.Teresa Gasparian Keutenedjian) | C48: =464.52+4590.59 -> 5055.11 | D48: 0 | E48: 0 | F48: 0 | G48: 0 | H48: 0 | I48: 0 | J48: 0 | K48: =C48 -> 5055.11 | L48: =D48 -> 0 | M48: 0 | N48: 0 | O48: 0 | P48: 0 | Q48: 0 | R48: 0 | S48: 0 | T48: 0 | U48: 0 | V48: 0 | W48: 0 | X48: 0
B49: Repasse(Maria Carolina K. Mady) | C49: 0 | D49: 0 | E49: 0 | F49: 0 | G49: 0 | H49: 0 | I49: 0 | J49: 0 | K49: 0 | L49: 0 | M49: 0 | N49: =C49 -> 0 | O49: 0 | P49: 0 | Q49: 0 | R49: 0 | S49: 0 | T49: 0 | U49: 0 | V49: 0 | W49: 0 | X49: 0
B50: Repasse(FKZ Inv.) | C50: 9181.19 | D50: 0 | E50: 0 | F50: 0 | G50: 0 | H50: 0 | I50: 0 | J50: 0 | K50: 0 | L50: 0 | M50: 0 | N50: 0 | O50: =C50 -> 9181.19 | P50: 0 | Q50: 0 | R50: 0 | S50: 0 | T50: 0 | U50: 0 | V50: 0 | W50: 0 | X50: 0
B51: Repasse (Thyago C. Keutenedjian) | C51: 0 | D51: 0 | E51: 0 | F51: =C51 -> 0 | G51: 0 | H51: 0 | I51: 0 | J51: 0 | K51: 0 | L51: 0 | M51: 0 | N51: 0 | O51: 0 | P51: 0 | Q51: 0 | R51: 0 | S51: 0 | T51: 0 | U51: 0 | V51: 0 | W51: 0 | X51: 0
B52: Repasse (Frederico C. Keutenedjian) | C52: =1838.73 -> 1838.73 | D52: 0 | E52: 0 | F52: 0 | G52: =C52 -> 1838.73 | H52: 0 | I52: 0 | J52: 0 | K52: 0 | L52: 0 | M52: 0 | N52: 0 | O52: 0 | P52: 0 | Q52: 0 | R52: 0 | S52: 0 | T52: 0 | U52: 0 | V52: 0 | W52: 0 | X52: 0
B53: Repasse (Caroline C. Keutenedjian) | C53: =1838.73 -> 1838.73 | D53: 0 | E53: =C53 -> 1838.73 | F53: 0 | G53: 0 | H53: 0 | I53: 0 | J53: 0 | K53: 0 | L53: 0 | M53: 0 | N53: 0 | O53: 0 | P53: 0 | Q53: 0 | R53: 0 | S53: 0 | T53: 0 | U53: 0 | V53: 0 | W53: 0 | X53: 0
B54: Repasse (Ropsimé Keutenedjian) | C54: =4645.21 -> 4645.21 | D54: 0 | E54: 0 | F54: 0 | G54: 0 | H54: 0 | I54: 0 | J54: 0 | K54: 0 | L54: 0 | M54: 0 | N54: 0 | O54: 0 | P54: 0 | Q54: 0 | R54: 0 | S54: 0 | T54: 0 | U54: =C54 -> 4645.21 | V54: 0 | W54: 0 | X54: 0
B55: Repasse (Roke Empreendimentos Ltda.) | C55: =44386.08 -> 44386.08 | D55: 0 | E55: 0 | F55: 0 | G55: 0 | H55: 0 | I55: 0 | J55: 0 | K55: 0 | L55: 0 | M55: 0 | N55: 0 | O55: 0 | P55: 0 | Q55: 0 | R55: 0 | S55: 0 | T55: 0 | U55: 0 | V55: 0 | W55: 0 | X55: =C55 -> 44386.08
B56: Repasse (Ropsime Claudina Keutenedjian) | C56: =5574.25+36202.96 -> 41777.21 | D56: =C56 -> 41777.21 | E56: 0 | F56: 0 | G56: 0 | H56: 0 | I56: 0 | J56: 0 | K56: 0 | L56: 0 | M56: 0 | N56: 0 | O56: 0 | P56: 0 | Q56: 0 | R56: 0 | S56: 0 | T56: 0 | U56: 0 | V56: 0 | W56: 0 | X56: 0
B57: Repasse (Hallejujah) | C57: 22136.16 | D57: 0 | E57: 0 | F57: 0 | G57: 0 | H57: 0 | I57: 0 | J57: 0 | K57: 0 | L57: 0 | M57: 0 | N57: 0 | O57: 0 | P57: 0 | Q57: 0 | R57: 0 | S57: 0 | T57: 0 | U57: 0 | V57: 0 | W57: =C57 -> 22136.16 | X57: 0
B58: Repasse (Keute) | C58: 22136.16 | D58: 0 | E58: 0 | F58: 0 | G58: 0 | H58: 0 | I58: 0 | J58: 0 | K58: 0 | L58: 0 | M58: 0 | N58: 0 | O58: 0 | P58: 0 | Q58: 0 | R58: 0 | S58: 0 | T58: 0 | U58: 0 | V58: =C58 -> 22136.16 | W58: =D58 -> 0 | X58: 0
B59: Ajustes de Saldos Individual | C59: 0 | D59: 0 | E59: 0 | F59: 0 | G59: 0 | H59: 0 | I59: 0 | J59: 0 | K59: 0 | L59: 0 | M59: 0 | N59: 0 | O59: 0 | P59: 0 | Q59: 0 | R59: 0 | S59: 0 | T59: 0 | U59: 0 | V59: 0 | W59: 0 | X59: 0
B60: SUB TOTAL: | C60: =SUM(C33:C59) -> 291756.23 | D60: =SUM(D33:D59) -> 52123.804 | E60: =SUM(E33:E59) -> 7086.4465 | F60: =SUM(F33:F59) -> 5247.7165 | G60: =SUM(G33:G59) -> 7086.4465 | H60: =SUM(H33:H59) -> 8523.4281 | I60: =SUM(I33:I59) -> 11422.064 | J60: =SUM(J33:J59) -> 11131.734 | ... X60: =SUM(X33:X59) -> 44386.08
B61: TOTAL DE DESPESAS: | C61: =-C14-C18-C25-C30-C60 -> -567237.19 | D61: =-D14-D18-D25-D30-D60 -> -118637.01 | E61: =-E14-E18-E25-E30-E60 -> -22868.579 | F61: =-F14-F18-F25-F30-F60 -> -18612.704 | G61: =-G14-G18-G25-G30-G60 -> -22868.579 | H61: =-H14-H18-H25-H30-H60 -> -9588.9106 | I61: =-I14-I18-I25-I30-I60 -> -24759.002 | J61: =-J14-J18-J25-J30-J60 -> -22051.527 | ... X61: =-X14-X18-X25-X30-X60 -> -59955.568

Sheet Saldo Individual
B5: SALDOS INDIVIDUAIS - MAIO/2026
C6: SALDO ANTERIOR | D6: RECEITAS DO MÊS | E6: DESPESAS DO MÊS | F6: SALDO ATUAL
B7: ROPSIME CLAUDINA VARAM KEUTENEDJIAN | C7: 18842.932 | D7: ='Dist. Receitas'!N303 -> 124254.23 | E7: ='Dist. Despesas'!D61 -> -118637.01 | F7: =C7+D7+E7 -> 24460.148
B9: CAROLINE CORDEIRO KEUTENEDJIAN | C9: 9797.9069 | D9: ='Dist. Receitas'!O303 -> 19462.523 | E9: ='Dist. Despesas'!E61 -> -22868.579 | F9: =C9+D9+E9 -> 6391.8514
B11: THYAGO BAPTISTA CORDEIRO KEUTENEDJIAN | C11: -41773.088 | D11: ='Dist. Receitas'!P303 -> 16389.493 | E11: ='Dist. Despesas'!F61 -> -18612.704 | F11: =C11+D11+E11 -> -43996.299
B13: FREDERICO CORDEIRO KEUTENEDJIAN | C13: 15584.597 | D13: ='Dist. Receitas'!Q303 -> 19462.523 | E13: ='Dist. Despesas'!G61 -> -22868.579 | F13: =C13+D13+E13 -> 12178.541
B15: KEUTE ADMINISTRAÇÃO E PARTICIPAÇÕES | C15: 9582.712 | D15: ='Dist. Receitas'!AF303 -> 30485.511 | E15: ='Dist. Despesas'!V61 -> -29920.904 | F15: =C15+D15+E15 -> 10147.319
B17: HALLELUJAH PARTICIPAÇÕES LTDA | C17: 9582.711 | D17: ='Dist. Receitas'!AG303 -> 30485.511 | E17: ='Dist. Despesas'!W61 -> -29920.904 | F17: =C17+D17+E17 -> 10147.318
B19: CLAUDINA VARAM KEUTENEDJIAN MAKHOUL | C19: 11411.459 | D19: ='Dist. Receitas'!S303 -> 24678.49 | E19: ='Dist. Despesas'!I61 -> -24759.002 | F19: =C19+D19+E19 -> 11330.946
B21: VARAM KEUTENEDJIAN NETO | C21: 7484.6618 | D21: ='Dist. Receitas'!T303 -> 21605.46 | E21: ='Dist. Despesas'!J61 -> -22051.527 | F21: =C21+D21+E21 -> 7038.5943
B23: MARIA TERESA GASPARIAN KEUTENEDJIAN | C23: 1468.8562 | D23: ='Dist. Receitas'!U303 -> 11013.95 | E23: ='Dist. Despesas'!K61 -> -11236.979 | F23: =C23+D23+E23 -> 1245.8274
B25: HENRIQUE GASPARIAN KEUTENEDJIAN | C25: 1468.8562 | D25: ='Dist. Receitas'!V303 -> 11013.95 | E25: ='Dist. Despesas'!L61 -> -11236.979 | F25: =C25+D25+E25 -> 1245.8274
B27: MARIA CAROLINA VARAM KEUTENEDJIAN MADY | C27: -392.06141 | D27: ='Dist. Receitas'!X303 -> 0 | E27: ='Dist. Despesas'!N61 -> -1472.5941 | F27: =C27+D27+E27 -> -1864.6555
B29: ADRIANA VARAM KEUTENEDJIAN ZIMMERMANN | C29: 343.91149 | D29: ='Dist. Receitas'!W303 -> 9833.6956 | E29: ='Dist. Despesas'!M61 -> -10178.88 | F29: =C29+D29+E29 -> -1.2728173
B31: FKZ INVESTIMENTOS E PARTICIPACOES | C31: -7198.3977 | D31: ='Dist. Receitas'!Y303 -> 12194.204 | E31: ='Dist. Despesas'!O61 -> -12295.088 | F31: =C31+D31+E31 -> -7299.2809
B33: CARLOS ANIBAL HADDAD | C33: 0 | D33: 0 | E33: ='Dist. Despesas'!M63 -> 0 | F33: =C33+D33+E33 -> 0
B35: JULIANA MATOS HADDAD | C35: -1485.2629 | D35: ='Dist. Receitas'!AA303 -> 14445.785 | E35: ='Dist. Despesas'!Q61 -> -18924.679 | F35: =C35+D35+E35 -> -5964.1568
B37: MONIQUE HADDAD LEWANDOWSKY | C37: 19689.101 | D37: ='Dist. Receitas'!AB303 -> 26737.905 | E37: ='Dist. Despesas'!R61 -> -26978.859 | F37: =C37+D37+E37 -> 19448.147
B39: VIVIANNE HADDAD MORUZZI | C39: 13630.041 | D39: ='Dist. Receitas'!AC303 -> 26737.905 | E39: ='Dist. Despesas'!S61 -> -26978.859 | F39: =C39+D39+E39 -> 13389.087
B41: DENISE HADDAD | C41: 16098.501 | D41: ='Dist. Receitas'!AD303 -> 27534.875 | E41: ='Dist. Despesas'!T61 -> -26980.429 | F41: =C41+D41+E41 -> 16652.947
B43: ROPSIMÉ KEUTENEDJIAN MILANI | C43: 53867.069 | D43: ='Dist. Receitas'!AE303 -> 49168.478 | E43: ='Dist. Despesas'!U61 -> -59062.677 | F43: =C43+D43+E43 -> 43972.87
B45: EDDA MILANI KEUTENEDJIAN | C45: -34856.618 | D45: ='Dist. Receitas'!R303 -> 0 | E45: ='Dist. Despesas'!H61 -> -9588.9106 | F45: =C45+D45+E45 -> -44445.529
B47: ROKE LTDA. | C47: 11220.144 | D47: ='Dist. Receitas'!AH303 -> 60971.022 | E47: ='Dist. Despesas'!X61 -> -59955.568 | F47: =C47+D47+E47 -> 12235.598
B49: MARCO ANTÔNIO KEUTENEDJIAN MILANI | C49: 1231.2671 | D49: ='Dist. Receitas'!Z303 -> 3073.0299 | E49: ='Dist. Despesas'!P61 -> -2707.4748 | F49: =C49+D49+E49 -> 1596.8221
